{
  "version": 1,
  "items": [
    {
      "question": "대한민국 최초의 인공위성과 발사 연도는?",
      "answer": "우리별 1호는 대한민국 최초의 인공위성으로 1992년에 발사되었다."
    },
    {
      "question": "누리호의 발사 결과는?",
      "answer": "누리호는 2021년에 발사하였지만 궤도 안착에 실패하였고, 2022년에 나로우주센터에서 2차 발사에 성공하였다."
    },
    {
      "question": "나로우주센터는 언제 준공되었는가?",
      "answer": "나로우주센터는 대한민국의 첫 번째 우주 센터로 2009년에 준공 완료되었다."
    },
    {
      "question": "우주 망원경의 장점은?",
      "answer": "대기의 영향을 받지 않으므로 지상 망원경보다 더 선명한 상을 얻을 수 있다."
    },
    {
      "question": "우주 탐사선의 장단점은?",
      "answer": "천체에 접근하여 자세하게 관측할 수 있는 장점이 있지만, 비용이 많이 들고 이동 시간이 길다는 단점이 있다."
    },
    {
      "question": "목성에서 측정한 연주 시차가 지구보다 큰 이유는?",
      "answer": "목성은 지구보다 공전궤도가 크기 때문에 두 관측지점 사이의 거리가 크므로 연주 시차도 더 크게 측정된다."
    },
    {
      "question": "목성에서 태양까지의 거리가 지구의 약 5배일 때 연주 시차는?",
      "answer": "두 관측지점 사이의 거리가 5배로 증가하기 때문에 측정되는 연주 시차도 약 5배이다."
    },
    {
      "question": "별까지의 거리가 4배 멀어지면 밝기는 어떻게 변하는가?",
      "answer": "별의 밝기는 거리의 제곱에 반비례하므로, 거리가 4배 멀어지면 밝기는 16배 어두워진다."
    },
    {
      "question": "연주 시차와 별까지의 거리 계산 공식은?",
      "answer": "거리(pc) = 1/연주시차(\")로 계산할 수 있다."
    },
    {
      "question": "별 S의 연주 시차가 0.2\"일 때 거리는?",
      "answer": "별까지의 거리는 1/0.2\" = 5pc이다."
    },
    {
      "question": "허블 우주 망원경은 언제 발사되었는가?",
      "answer": "허블 우주 망원경은 1990년에 발사된 우주 망원경으로 천문학자 허블의 이름을 따온 것이다."
    },
    {
      "question": "무궁화 1호는 언제 발사되었는가?",
      "answer": "무궁화 1호는 1995년에 발사되었다."
    },
    {
      "question": "별빛이 진행한 거리가 멀수록 나타나는 현상은?",
      "answer": "별빛이 진행한 거리가 멀수록 비추는 면적이 넓어지기 때문에 일정 범위에 도달하는 빛의 양이 감소하여 별이 어둡게 보인다."
    },
    {
      "question": "연주 시차가 클수록 별의 위치는?",
      "answer": "연주 시차가 클수록 더 가까운 곳에 별이 위치한다."
    },
    {
      "question": "태양의 색깔은 무엇이며 표면 온도 순서에서 어디에 위치하는가?",
      "answer": "태양은 노란색이며, 표면 온도 순서에서 베텔게우스(붉은색)보다 높고 프로키온(황백색)보다 낮은 온도를 가진다."
    }
  ]
}