{
  "version": 1,
  "items": [
    {
      "question": "현재 한국에서 생산되는 연필은?",
      "answer": "동아연필이 아직도 연필을 생산하고 있다. 모나미도 예전에 연필을 만들었으나 현재는 생산하지 않는다."
    },
    {
      "question": "문화연필은 어떤 제품을 만들었는가?",
      "answer": "사파이어, 흑진주 등 하이엔드 연필을 만들었다. 현재는 중국으로 넘어갔다."
    },
    {
      "question": "한국 연필의 명작으로 꼽히는 제품들은?",
      "answer": "사파이어, 흑진주, 은구슬, 꽃송이, 푸른동산, 옥토끼 등이 있다. 모두 아름다운 이름을 가졌다."
    },
    {
      "question": "사파이어 연필의 가격은?",
      "answer": "50원짜리로 당시 하이엔드 연필이었다. 버스비가 10원이던 시절이었다."
    },
    {
      "question": "한국이 연필 제조에 유리한 조건을 가진 이유는?",
      "answer": "흑연 매장량이 전 세계 손꼽히는 수준이고, 물이 맑으며, 도자기 기술로 점토와 불을 다룰 수 있고, 북한 강계군에 좋은 소나무가 있다."
    },
    {
      "question": "일제강점기에 한국에서 연필을 생산하지 못한 이유는?",
      "answer": "일본이 한국 사람들이 똑똑한 것을 알고 두려워하여 연필과 노트 생산을 금지했다. 공부와 연결되는 것을 막았다."
    },
    {
      "question": "한국은 언제부터 연필을 만들기 시작했는가?",
      "answer": "해방 직후부터 바로 연필을 만들기 시작했다. 기술과 재료가 다 있었기 때문이다."
    },
    {
      "question": "1970~80년대 한국 연필이 하이엔드였던 이유는?",
      "answer": "흑연, 물, 점토 기술, 좋은 나무, 쉬운 한글 등 모든 조건이 갖춰져 있었기 때문이다."
    },
    {
      "question": "박종진 소장이 수집을 권장하는 한국 연필은?",
      "answer": "블랙윙이나 카스텔 9000보다 사파이어, 흑진주 등 옛날 한국 연필을 수집해야 한다고 강조한다. 완성도가 높다."
    },
    {
      "question": "옥토끼 연필의 가격 표시 방식은?",
      "answer": "옥토끼 50, 60, 70, 100 등으로 표시되는데, 이는 가격을 의미한다. 50원, 60원, 70원, 100원이었다."
    },
    {
      "question": "박종진 소장이 흑진주와 사파이어를 원하는 이유는?",
      "answer": "외국 연필보다 더 갖고 싶어 한다. 한국 연필의 우수성을 인정하며, 복각되면 계속 구매하겠다고 밝혔다."
    },
    {
      "question": "박종진 소장이 연필 회사에 제안하는 것은?",
      "answer": "블랙윙처럼 흑진주, 사파이어 등 옛날 명품 연필을 복각해야 한다고 제안한다. 커피 대신 연필을 사겠다고 말한다."
    },
    {
      "question": "연필 수집에서 옛날 한국 연필을 찾는 방법은?",
      "answer": "오래된 문방구의 구석에 처박혀 있던 안 팔린 연필들을 찾아다닌다."
    },
    {
      "question": "연필이 좋은 필기구인 이유는 무엇인가?",
      "answer": "지워진다는 점이 가장 큰 장점이다. 연필을 제외한 모든 필기구는 지울 수 없다."
    },
    {
      "question": "지우개가 연필에 붙게 된 시기는?",
      "answer": "1800년대 중반이다. 연필 탄생 후 한참 뒤에 붙었다."
    },
    {
      "question": "지우개가 연필에 붙은 시대적 배경은?",
      "answer": "미국이 융성하고 이념 대결(남북전쟁)이 많던 시기에 지우개가 붙었다."
    },
    {
      "question": "연필과 함께 발전한 사회적 배경은?",
      "answer": "1564년 영국에서 흑연 발견은 엘리자베스 여왕 시대, 셰익스피어 출생 시기로 영국 문화 융성기였다."
    },
    {
      "question": "레오나르도 다빈치에게 연필이 있었다면?",
      "answer": "작품이 배 이상 많았을 것이다. 연필은 실용적이고 능률적이며 지울 수 있어 매우 유용했을 것이다."
    },
    {
      "question": "연필 제작에 필요한 오행 요소는?",
      "answer": "흑연(흙), 물, 점토를 다루는 불, 나무 등 오행이 모두 들어간다."
    }
  ]
}