{
  "version": 1,
  "items": [
    {
      "question": "독일에서 만년필 펜 촉(닙)을 생산하는 공장은 몇 개나 있으며, 그 특징은?",
      "answer": "독일 전체에 단 두 곳뿐이다. 보안이 매우 철저하여 문마다 별도 잠금장치가 있으며, 자신들의 기술 노하우를 절대 외부에 공개하지 않는다."
    },
    {
      "question": "촉 공장 방문이 어떻게 성사되었으며, 슈미트 회장의 역할은?",
      "answer": "한 달간의 협상 끝에 촬영 금지와 슈미트 회장 동행 조건으로 방문이 성사되었다. 슈미트 회장 역시 그 공장을 처음 방문한 것으로, 새벽 비행기를 타고 합류했다."
    },
    {
      "question": "촉 공장 사장의 경계심이 풀린 계기는 무엇인가?",
      "answer": "사장이 사용하던 만년필을 박종진 소장이 보고 '피드는 이탈리아제이고 촉은 따로 조립한 것'이라고 정확히 맞혔기 때문이다. 같은 루페를 목에 걸고 있던 만년필 매니아임을 확인하면서 태도가 급격히 우호적으로 바뀌었다."
    },
    {
      "question": "촉 공장에서 사용하는 이리듐 포인트 관련 중요한 발견은 무엇인가?",
      "answer": "일반적으로 스틸 촉과 금촉은 서로 다른 품질의 이리듐 포인트를 사용하는데, 이 공장은 스틸 촉과 금촉에 동일한 고품질 이리듐(헤라우스/Heraeus 제품)을 사용한다는 것을 확인했다."
    },
    {
      "question": "이번 독일 출장에서 슈미트 및 촉 공장과 합의한 공급 일정은?",
      "answer": "스틸 촉(총 1만 5천 개)은 11월 말부터 월 5천 개씩 3개월간 공급하고, 금촉(1만 개)은 2월부터 공급을 시작하여 4월에 완료할 예정이다."
    },
    {
      "question": "이번 주문 물량이 촉 공장에서 얼마나 큰 규모인지 비교 설명하라.",
      "answer": "몽블랑 한정판이 최대 1,500개, 일반 브랜드는 200~500개 수준인데, 이번 주문은 금촉 1만 개로 몽블랑의 약 10배에 달하는 대규모 주문이었다. 공장 측에서 처음에는 수량을 믿지 못했다."
    },
    {
      "question": "차기 만년필 프로젝트와 관련하여 촉 공장과 합의한 장기 계획은?",
      "answer": "6개월 전부터 사전 협의를 거쳐 한국인의 필기 특성에 최적화된 촉 모양(금형)을 새로 만들기로 합의했다. 한글 특성에 맞는 맞춤형 촉을 공동 개발하는 것이 목표다."
    },
    {
      "question": "독일 촉 공장의 기술적 뿌리는 어디서 비롯되었는가?",
      "answer": "동독에서 넘어온 기술이 뿌리이며, 독일 통일 이후 서독에서 인수한 것이다. 이 역사적 배경이 그들의 기술 자부심과 강한 보안 의식의 토대가 되었다."
    },
    {
      "question": "'박종진 터치'란 무엇이며, 만년필 제작 공정에서 어떤 역할을 하는가?",
      "answer": "공장에서 완성된 촉을 박종진 소장이 직접 손으로 다듬고 조정하는 마지막 공정이다. 한글 필기 특성에 맞게 폴리시(polish)하는 작업으로, 이 작업 때문에 소장은 현재 손가락을 철저히 보호하고 있다."
    },
    {
      "question": "박종진 소장의 '터치' 생산 능력의 한계는 어느 정도인가?",
      "answer": "한 달에 최대 5,000개까지만 터치 작업이 가능하다. 이를 고려하여 스틸 촉 1만 5천 개를 3개월에 걸쳐 월 5천 개씩 처리하는 일정을 수립했다."
    },
    {
      "question": "촉 공장 측이 박종진 소장의 촉 조정 요구(베이비 바텀 조정)를 거부한 이유는?",
      "answer": "소장이 원하는 방식으로 촉을 조정하면 공장의 자체 기준에서는 '불량품'이 되기 때문이다. 공장은 자신들의 기준에 맞지 않는 제품은 출하할 수 없다는 입장을 고수했다."
    },
    {
      "question": "박종진 소장이 기차에서 창밖의 소를 보고 한 말과 그 결론은?",
      "answer": "'독일 소는 작아'라고 주장했으며, 현지 독일인들은 이를 부정했다. 그러나 이후 기차 안에서 논문을 검색한 결과, 독일 남부 고지대 방목 소는 평균 10센티미터 더 작다는 사실이 학술 논문으로 확인되었다."
    },
    {
      "question": "독일 남부 고지대에 방목되는 소의 외형적 특징은?",
      "answer": "얼굴에 털이 북슬북슬하고 뿔이 얇고 뾰족하다. 기차가 시속 200km로 달리는 중에도 박종진 소장은 순간적으로 소의 크기와 생김새를 정확히 파악했다."
    },
    {
      "question": "박종진 소장이 발견한 독일 냅킨의 차이점은?",
      "answer": "독일 냅킨은 세로 7mm, 가로 4mm가 일반 냅킨보다 더 크다. 소장이 귀국 후 냅킨을 실제로 측정하여 확인했다."
    },
    {
      "question": "박종진 소장이 슈미트 본사 회의에서 주목한 참석자들의 특이한 기록은?",
      "answer": "회의 내용 대신 참석자들의 필기구 상태를 기록했다. '클라우디아 만년필 잉크 마름', '슈미트 회장 롤러볼', '헬무트 포르쉐 디자인 만년필' 등을 수첩에 남겼다."
    },
    {
      "question": "슈미트 본사 방문 시 독일 지역사회에서 눈에 띈 점은?",
      "answer": "슈바르츠발트는 여행지가 아닌 곳이라 동양인 5명이 내리자 현지인들이 모두 의아해하며 쳐다봤다. 빵집에서도 왜 동양인이 거기 있냐며 계속 쳐다봤다고 한다."
    },
    {
      "question": "이번 독일 출장에서 계약 서명 시 사용한 필기구는?",
      "answer": "김어준은 파카(Parker) 75로, 박종진 소장은 파카 51로 서명했다. 소장이 잉크가 더 잘 나오는 51을 선택했다."
    }
  ]
}