{
  "version": 1,
  "items": [
    {
      "question": "벤젠 고리에서 이중결합이 등장하는 이유는?",
      "answer": "탄소 6개가 고리를 만들면 각 탄소의 팔 4개 중 위아래 2개는 탄소끼리, 1개는 수소와 연결하면 팔 1개가 남는다. 이 남는 팔들이 인접 탄소 사이에 이중결합(=)을 형성한다. 벤젠 고리에는 이중결합 3개가 교차하여 존재한다."
    },
    {
      "question": "벤젠 고리의 공명(resonance) 이론이란?",
      "answer": "벤젠 고리에서 단일결합과 이중결합의 길이를 측정하면 이론상 달라야 하는데 실제로 모두 같다. 이는 이중결합 전자가 정지하지 않고 고리 안을 계속 이동(공명)하기 때문이다. 이는 양자역학적 전자구름의 확률 분포 현상이다."
    },
    {
      "question": "선크림(자외선 차단제)의 원리를 벤젠 고리로 설명하면?",
      "answer": "태양빛(포톤)은 약 만 도(1 eV ≈ 11,600 K)에 해당하는 에너지를 가져 피부 세포를 파괴할 수 있다. 선크림 속 벤젠 고리가 포톤을 흡수하면, 공명하는 전자가 고리 안에서 포톤 에너지를 가두어 피부까지 전달되지 않게 차단한다."
    },
    {
      "question": "페놀(phenol)이란 무엇이며 어떻게 만들어지는가?",
      "answer": "벤젠 고리의 수소 6개 중 1개를 OH로 교체한 물질이다. 나무를 태울 때 나오는 콜타르(목청)에서 추출할 수 있으며, 현재는 석유화학 공정으로 만든다."
    },
    {
      "question": "페놀이 의학 역사에서 중요한 이유는?",
      "answer": "영국 외과의사 리스터(Lister)가 페놀(석탄산)을 수술 소독제로 사용해 수술 중 감염 사망률을 획기적으로 줄였다. 당시 수술 중 약 50%가 감염으로 사망했으나, 페놀 소독 이후 생존율이 크게 향상되었다."
    },
    {
      "question": "페놀이 당구공과 코끼리 보호에 기여한 이유는?",
      "answer": "과거 당구공은 상아(코끼리 엄니)로 만들었다. 페놀과 알데하이드를 합성해 최초의 인조 플라스틱(베이클라이트)을 만들어 당구공을 대체함으로써 코끼리 남획을 줄이는 데 기여했다."
    },
    {
      "question": "콜레스테롤의 구조적 특징은?",
      "answer": "콜레스테롤은 탄소 27개로 이루어진 분자로, 육각형 3개와 오각형 1개가 결합한 벌집 모양 구조이다. 주로 간에서 합성되며, 합성 과정이 약 20단계로 복잡하고 인체 스스로 분해하지 못한다."
    },
    {
      "question": "콜레스테롤의 인체 내 역할은?",
      "answer": "① 담즙산으로서 지방 소화·흡수 도움(하루 약 1리터 분비), ② 세포막의 유동성 유지, ③ 신경세포 시냅스 막에서 단백질을 고정하는 '앵커' 역할(지질 뗏목 형성). 콜레스테롤이 없으면 정신 작용과 지방 흡수가 불가능하다."
    },
    {
      "question": "시냅스에서 콜레스테롤의 역할을 구체적으로 설명하면?",
      "answer": "두 신경세포가 만나는 시냅스 막에는 단백질이 1000개 이상 박혀 있다. 단백질들이 제 기능을 하려면 막에 고정되어야 하는데, 콜레스테롤이 지질 뗏목을 형성해 단백질을 일정 위치에 닻(앵커)처럼 고정시켜 신경 신호 전달을 가능하게 한다."
    },
    {
      "question": "유기화학과 생화학의 관계는?",
      "answer": "유기화학은 탄소로 연결된 분자(사슬·고리 두 형태)를 연구하는 학문이다. 생화학은 유기화학의 부분집합이며, 뇌과학·세포생물학 등 모든 생물학은 생화학의 부분집합이다. 즉 모든 생명과학은 유기화학 위에 세워진다."
    },
    {
      "question": "지구상의 유기 분자는 몇 종류나 알려져 있는가?",
      "answer": "탄소로 연결된 유기 분자는 지금까지 발견·합성된 것만 1억 개가 넘는다. 이 모두가 탄소 사슬 또는 벤젠 고리의 변주(베리에이션)이며, '인간 문화'라고 표현할 수 있다."
    },
    {
      "question": "톨루엔(toluene)이란 무엇인가?",
      "answer": "벤젠 고리 수소 6개 중 하나를 메틸기(CH₃)로 교체한 물질이다. 고등학교 화학에도 등장하는 기초 유기화합물로, TNT 폭약 합성의 출발 물질이 된다."
    },
    {
      "question": "TNT(트리니트로톨루엔)는 어떻게 만들어지는가?",
      "answer": "톨루엔(벤젠 고리에 CH₃ 1개)에 추가로 니트로기(NO₂) 3개를 붙이면 쓰리 니트로 톨루엔(TNT)이 된다. 1차 세계대전에서 독일이 TNT를 사용해 피크르산(페놀 기반 폭약)을 쓰던 영국·프랑스보다 화력에서 앞섰다."
    },
    {
      "question": "폭약에서 NO₂(니트로기)가 중요한 이유는?",
      "answer": "폭발은 연소이므로 산소가 필요한데, 외부 공기 중 산소를 끌어오면 시간이 걸려 폭발력이 약하다. NO₂에는 산소 2개가 포함되어 있어, 폭약 분자 자체가 산소를 공급한다. 이것이 폭약의 핵심 원리이다."
    }
  ]
}