{
  "version": 1,
  "items": [
    {
      "question": "다항식의 나눗셈에서 나머지의 자격 조건은 무엇인가요?",
      "answer": "나머지는 반드시 나누는 식보다 차수가 낮아야 합니다. 예를 들어 2차식으로 나누면 나머지는 1차 이하(1차 또는 상수)가 되어야 합니다."
    },
    {
      "question": "다항식의 나눗셈을 세로 셈으로 할 때 기본 원리는 무엇인가요?",
      "answer": "최고차항만 보고 계산합니다. 나누는 식의 최고차항에 무엇을 곱해야 나누어지는 식의 최고차항이 되는지 생각하여 몫을 구하고, 곱한 결과를 빼는 과정을 반복합니다."
    },
    {
      "question": "다항식 나눗셈에서 1차항이 없을 때는 어떻게 처리하나요?",
      "answer": "빈자리를 만들어줍니다. 예를 들어 $3x^3-4x^2-7$은 1차항이 없으므로 $3x^3-4x^2+0x-7$로 생각하고 계산하면 편리합니다."
    },
    {
      "question": "$4x^3-4x^2+x-5$를 $x^2-4x+1$로 나눈 몫과 나머지를 구하는 과정은 어떻게 되나요?",
      "answer": "최고차항끼리 비교하여 $4x$를 곱하고 빼면 $12x^2-3x-5$가 됩니다. 다시 $12$를 곱하고 빼면 $45x-17$이 나옵니다. 몫은 $4x+12$, 나머지는 $45x-17$입니다."
    },
    {
      "question": "$3x^3-4x^2-7$을 $x^2+2$로 나눈 몫과 나머지는 무엇인가요?",
      "answer": "최고차항 비교로 $3x$를 곱하고 빼면 $-4x^2-6x-7$이 됩니다. 다시 $-4$를 곱하고 빼면 $-6x+1$이 나옵니다. 몫은 $3x-4$, 나머지는 $-6x+1$입니다."
    },
    {
      "question": "다항식을 2차식이나 3차식으로 나눌 때는 어떤 방법을 사용하나요?",
      "answer": "직접 나눗셈(세로 셈)을 사용합니다. 최고차항을 비교하며 계산하는 방법밖에 없습니다."
    },
    {
      "question": "조립제법이란 무엇인가요?",
      "answer": "1차식으로 나눈 몫과 나머지를 구하는 가장 쉬운 방법입니다. 계수만 가지고 나눗셈을 계산하는 방법으로, 2차식이나 3차식으로는 사용할 수 없습니다."
    },
    {
      "question": "조립제법을 사용할 수 있는 조건은 무엇인가요?",
      "answer": "1차식으로 나눌 때만 사용 가능합니다. 특히 1차식의 최고차항 계수가 1일 때를 기준으로 만들어진 방법입니다."
    },
    {
      "question": "조립제법의 첫 번째 단계는 무엇인가요?",
      "answer": "나누어지는 식의 계수를 최고차항부터 순서대로 씁니다. 빠진 차수가 있으면 0을 써서 빈자리를 채웁니다."
    },
    {
      "question": "조립제법에서 ㄴ자 모양 왼쪽에 쓰는 숫자는 무엇인가요?",
      "answer": "나누는 1차식을 0으로 만드는 $x$값입니다. 예를 들어 $x+1$로 나누면 $-1$을, $x-2$로 나누면 $2$를 씁니다."
    },
    {
      "question": "조립제법의 계산 과정은 어떻게 진행되나요?",
      "answer": "첫 번째 계수를 그대로 내려쓰고, 이를 왼쪽 숫자와 곱해서 다음 자리 아래에 씁니다. 두 수를 더하고 이 과정을 반복합니다. 곱하기와 더하기만 사용합니다."
    },
    {
      "question": "$x^3+5x^2-x-2$를 $x+1$로 나눌 때 조립제법은 어떻게 사용하나요?",
      "answer": "계수 1, 5, -1, -2를 쓰고 왼쪽에 -1을 씁니다. 1을 내리고, $1 \\times (-1) = -1$을 쓰고 $5+(-1)=4$를 계산하는 식으로 진행하여 몫 $x^2+4x-5$, 나머지 3을 얻습니다."
    },
    {
      "question": "조립제법에서 맨 마지막에 나온 숫자는 무엇인가요?",
      "answer": "나머지입니다. 1차식으로 나눈 나머지는 항상 상수이므로 마지막 자리에 나머지가 위치합니다."
    },
    {
      "question": "조립제법에서 나머지를 제외한 숫자들은 무엇을 나타내나요?",
      "answer": "몫의 계수들입니다. 오른쪽부터 상수항, 1차항, 2차항 순서로 읽어 몫을 구성합니다."
    },
    {
      "question": "$x^4-3x^2+5x-1$을 $x-2$로 나눌 때 조립제법의 첫 단계는 무엇인가요?",
      "answer": "계수를 1, 0, -3, 5, -1로 씁니다. 3차항이 없으므로 0을 써서 빈자리를 채우고, 왼쪽에 2를 씁니다."
    },
    {
      "question": "$x^4-3x^2+5x-1$을 $x-2$로 나눈 몫과 나머지는 무엇인가요?",
      "answer": "조립제법으로 계산하면 몫은 $x^3+2x^2+x+7$, 나머지는 13입니다."
    },
    {
      "question": "조립제법은 왜 1차식으로만 나눌 수 있나요?",
      "answer": "조립제법은 최고차항 계수가 1인 1차식으로 나누는 것을 기준으로 만들어진 방법이기 때문입니다. 2차식이나 3차식으로는 직접 나눗셈을 해야 합니다."
    },
    {
      "question": "개념 공부와 수학 공부의 차이는 무엇인가요?",
      "answer": "개념 공부는 수학 내용을 소개받는 오리엔테이션 단계입니다. 수학 공부는 개념이 끝난 후 고난도 문제에서 출제 의도를 찾아내며 사고력을 키우는 것입니다."
    },
    {
      "question": "개념서의 단원마무리 문제는 어떻게 접근해야 하나요?",
      "answer": "먼저 한 번 풀어보고 설명을 듣는 것이 좋습니다. 단, 반드시 설명을 들어야 하며 새로운 개념도 거기서 설명하므로 건너뛰면 안 됩니다."
    },
    {
      "question": "다항식의 덧셈과 뺄셈을 효율적으로 하는 방법은 무엇인가요?",
      "answer": "모두 전개한 후 동류항을 처리하는 것이 아니라, 필요한 차수의 항만 바로 뽑아냅니다. 최고차항부터 차례대로 해당 차수 항들만 추출하여 계산합니다."
    }
  ]
}