{
  "version": 1,
  "items": [
    {
      "question": "항등식 문제에서 나온 연립방정식 $2a + b = 1$, $ab = -15$의 해는?",
      "answer": "$b = 1 - 2a$를 두 번째 식에 대입하면 $a(1 - 2a) = -15$, 즉 $2a^2 - a - 15 = 0$입니다. 인수분해하면 $(a + 3)(2a - 5) = 0$이므로 $a = -3$, $b = 7$ 또는 $a = \\frac{5}{2}$, $b = -6$입니다."
    },
    {
      "question": "항등식에서 양변의 차수가 다를 수 있나요?",
      "answer": "항등식이 성립하려면 양변의 최고차항 계수부터 상수항까지 모든 계수가 일치해야 하므로, 실질적으로 양변의 차수는 같아야 합니다. 차수가 다르면 높은 차수 항의 계수가 0이어야 합니다."
    },
    {
      "question": "수치대입법에서 같은 수를 여러 번 대입하면 안 되는 이유는?",
      "answer": "같은 수를 대입하면 동일한 식을 반복해서 얻게 되어 독립적인 방정식을 만들 수 없습니다. 미정계수 $n$개를 구하려면 $n$개의 독립적인 식이 필요합니다."
    },
    {
      "question": "항등식 $2x^2 + 3 = (x - 1)Q(x) + ax + b$에서 나눗셈을 수행하는 방법은?",
      "answer": "$2x^2 + 3$을 $x - 1$로 나눕니다. 조립제법이나 다항식 나눗셈을 사용하면 몫 $Q(x) = 2x + 2$, 나머지 $5$를 얻습니다."
    },
    {
      "question": "$2x^2 + 3$을 $x - 1$로 나눈 몫과 나머지는?",
      "answer": "조립제법을 사용하면 몫은 $Q(x) = 2x + 2$이고 나머지는 $5$입니다. 따라서 $2x^2 + 3 = (x - 1)(2x + 2) + 5$가 성립합니다."
    },
    {
      "question": "항등식 $2x^2 + 3 = (x - 1)(2x + 2) + 5$를 $ax + b$ 형태의 나머지와 비교하면?",
      "answer": "나머지가 $5 = ax + b$이므로, 이것은 $0 \\cdot x + 5$를 의미합니다. 따라서 $a = 0$, $b = 5$입니다."
    },
    {
      "question": "계수비교법과 수치대입법을 동시에 사용할 수 있나요?",
      "answer": "네, 가능합니다. 경우에 따라 한 방법으로 일부 계수를 구하고, 다른 방법으로 나머지 계수를 구하는 것이 더 효율적일 수 있습니다."
    },
    {
      "question": "항등식에서 $x$의 계수가 0이라는 것은 무엇을 의미하나요?",
      "answer": "$x$ 항이 존재하지 않는다는 의미입니다. 즉, 해당 항등식에는 상수항과 $x^2$ 이상의 고차항만 존재합니다."
    },
    {
      "question": "미정계수법을 사용할 때 검산하는 방법은?",
      "answer": "구한 계수 값을 원래 항등식에 대입하여 확인합니다. 여러 $x$ 값(특히 구할 때 사용하지 않은 값)을 대입하여 양변이 일치하는지 검증합니다."
    },
    {
      "question": "항등식 문제에서 '모든 $x$에 대하여'라는 조건이 중요한 이유는?",
      "answer": "이 조건이 항등식과 방정식을 구분하는 핵심입니다. 이 조건으로 인해 모든 동류항의 계수를 비교하거나 임의의 수를 대입할 수 있게 됩니다."
    },
    {
      "question": "계수비교법에서 전개 후 정리하는 과정이 중요한 이유는?",
      "answer": "동류항끼리 모아야 각 차수별 계수를 정확히 파악할 수 있기 때문입니다. 정리하지 않으면 같은 차수의 항들이 여러 곳에 흩어져 계수 비교가 어렵습니다."
    },
    {
      "question": "수치대입법에서 특수한 값(0, 1, -1)을 선호하는 이유는?",
      "answer": "이러한 값들은 계산을 단순화시켜줍니다. 0은 많은 항을 소거하고, 1과 -1은 부호 변화를 쉽게 확인할 수 있게 하며, 계산 실수를 줄여줍니다."
    },
    {
      "question": "$2a + b = 1$, $ab = -15$를 풀 때 이차방정식이 나오는 이유는?",
      "answer": "첫 번째 식에서 $b$를 $a$로 표현하여 두 번째 식에 대입하면 $a$에 대한 이차방정식이 됩니다. $a(1-2a) = -15$를 정리하면 $2a^2 - a - 15 = 0$이 됩니다."
    },
    {
      "question": "항등식 $2x^2 + x - 15 = (x + a)(2x + b)$의 해가 2개인 이유는?",
      "answer": "미정계수를 구하는 과정에서 이차방정식 $2a^2 - a - 15 = 0$이 나오기 때문입니다. 이차방정식은 일반적으로 2개의 해를 가지므로 $(a, b)$ 쌍도 2개가 됩니다."
    },
    {
      "question": "항등식의 미정계수를 구할 때 가장 먼저 확인해야 할 것은?",
      "answer": "미정계수의 개수를 파악하는 것입니다. 미정계수가 $n$개이면 $n$개의 독립적인 방정식이 필요하므로, 이에 맞게 계수비교나 수치대입을 계획해야 합니다."
    }
  ]
}