{
  "version": 1,
  "items": [
    {
      "question": "홍계월전의 주인공 홍계월의 이름은 어떤 의미를 담고 있는가?",
      "answer": "계수나무를 받았다는 의미와 달에 있다는 뜻으로 '계월'이라 지었다. 달나라 선녀를 의미하며, 옛날 사람들은 이 이름만으로도 주인공이 매우 아름다운 여성임을 알 수 있었다."
    },
    {
      "question": "홍계월전이 다른 여장군 소설들과 다른 가장 큰 특징은 무엇인가?",
      "answer": "대부분의 여장군 소설은 여주인공이 남장하여 장군이 된 후 현모양처로 돌아가는 것으로 끝나지만, 홍계월전은 여장군이 부하를 남편으로 취하는 독특한 설정을 가지고 있다."
    },
    {
      "question": "군담 소설이란 무엇이며, 우리나라 소설에서 차지하는 비중은?",
      "answer": "군담 소설은 전쟁과 나라에 대한 충성을 다루는 군대 이야기이다. 우리나라 소설 중 약 70%의 점유율을 차지하며, 주로 남자 주인공이 등장한다."
    },
    {
      "question": "홍계월전에서 군담 소설의 배경을 중국으로 설정한 이유는?",
      "answer": "조선을 배경으로 전쟁 이야기를 쓰면 정치적으로 문제가 될 수 있기 때문에 안전을 위해 중국을 배경으로 했다. SF에서 우주를 배경으로 하는 것과 유사한 방식이다."
    },
    {
      "question": "곽도사가 어린 계월의 관상을 본 후 어떤 예언을 했는가?",
      "answer": "다섯 살에 부모를 이별하고 이리저리 떠돌 것이라고 예언했다. 이 예언 때문에 부모는 계월을 남자 옷을 입히고 남자처럼 키우기로 결정했다."
    },
    {
      "question": "계월의 부모가 계월을 남자처럼 키운 이유는?",
      "answer": "곽도사의 불길한 예언(다섯 살에 부모와 이별하고 떠돌 것)을 피하기 위해 성별을 바꾸면 액운이 지나갈 수 있다고 생각했다."
    },
    {
      "question": "반란으로 인해 흩어진 계월의 가족은 각각 어떻게 되었는가?",
      "answer": "아버지는 반란군에 잡혔다가 벽파도로 귀양을 갔고, 어머니는 도적에게 잡혔다가 탈출하여 비구니가 되었으며, 계월은 강물에 떠내려갔다가 여공에게 구조되어 양자로 입양되었다."
    },
    {
      "question": "계월이 강물에 떠내려간 후 누구에게 구조되었는가?",
      "answer": "여공이라는 사람에게 구조되었다. 여공은 계월을 양자로 삼아 자신의 아들 여보국과 함께 키웠으며, 이름을 '홍평국'으로 바꿔주었다."
    },
    {
      "question": "'평국'이라는 이름이 '보국'보다 더 큰 의미를 가지는 이유는?",
      "answer": "보국은 '나라를 지킨다'는 의미인 반면, 평국은 '나라를 평안하게 한다(평천하)'는 의미로 스케일이 더 크다. 이름만으로도 계월이 더 출세할 것임을 암시한다."
    },
    {
      "question": "계월과 보국이 곽도사 밑에서 공부할 때 나타난 능력 차이는?",
      "answer": "계월은 부술책을 한 달 만에 깨쳤지만, 보국은 1년이 지나서야 겨우 배웠다. 15살에 과거 시험에서도 계월은 장원 급제, 보국은 차석을 했다."
    },
    {
      "question": "계월이 대원수가 되는 과정은?",
      "answer": "가달이라는 나라가 명나라를 공격했을 때, 황제가 대신들과 의논하는 순간 계월이 도착하여 즉시 대원수로 임명되었다. 보국은 중군장이 되었다."
    },
    {
      "question": "황제가 군영을 방문했을 때 계월이 보여준 군율은?",
      "answer": "황제가 왔음에도 대원수의 명령 없이는 문을 열 수 없다고 했고, 황제가 조서를 보낸 후에야 문을 열었다. 또한 군율에 따라 황제도 말에서 내려 걸어 들어오게 했으며, 큰절 대신 한쪽 다리만 구부려 인사했다."
    },
    {
      "question": "보국이 전쟁터에서 위기에 처했을 때 계월은 어떻게 했는가?",
      "answer": "적장을 베지 못하면 징을 쳐서 부르지 말라고 명령했음에도, 보국이 포위되자 직접 나가 적들을 쳐내고 보국을 옆구리에 껴서 구출했다."
    },
    {
      "question": "계월이 보국을 구출한 다음 날 어떤 조치를 취했는가?",
      "answer": "보국을 장군대 앞으로 불러 적장의 머리를 베지 못한 죄로 군법에 따라 목을 치려 했다. 다른 장수들이 간청하여 겨우 용서했지만, 이는 군율을 확립하고 보국을 다시는 위험에 빠지지 않게 하려는 의도였다."
    },
    {
      "question": "계월의 여성 정체가 밝혀진 계기는?",
      "answer": "계월이 병이 들어 황제가 보낸 어의가 진맥을 했는데, 맥이 여자의 맥이었다. 어의가 황제에게 보고했고, 이후 계월이 직접 상소를 올려 여성임을 밝혔다."
    },
    {
      "question": "계월이 여성임이 밝혀졌을 때 시녀들의 반응은?",
      "answer": "시녀들은 계월과 함께 눈물을 흘렸다. 이는 재능 있는 여성이 성별 때문에 규방에 갇혀 살아야 하는 불공평한 시대에 대한 슬픔과 공감을 상징한다."
    }
  ]
}