{
  "version": 1,
  "items": [
    {
      "question": "양성자의 내부 구조는 어떻게 되어 있는가?",
      "answer": "양성자는 세 개의 쿼크(업 쿼크 2개 + 다운 쿼크 1개)와 이들을 결합시키는 글루온(gluon, 아교풀 역할)으로 이루어져 있다. 중성자는 다운 쿼크 2개 + 업 쿼크 1개로 구성된다."
    },
    {
      "question": "글루온(gluon)이란?",
      "answer": "양성자나 중성자 내부에서 세 개의 쿼크를 결합시키는 역할을 하는 입자이다. 이름은 아교풀(glue)에서 유래했으며, 엿처럼 쿼크들을 묶어두는 접착제 같은 존재이다."
    },
    {
      "question": "양성자 내부에 구조가 있다는 것을 어떻게 알게 되었는가?",
      "answer": "전자를 양성자에 충돌시켜 튕겨져 나오는 각도를 분석하면 내부 구조를 알 수 있다. 마치 장님이 지팡이로 지형을 파악하듯, 작은 입자를 던져서 내부를 탐색하는 원리이다."
    },
    {
      "question": "가속기에서 수천 개의 새로운 입자가 탄생하자 물리학자들은 어떻게 대응했는가?",
      "answer": "너무 많은 입자가 쏟아져 나오자 먼저 분류가 필요하다고 판단했다. 유연한 사고를 가진 물리학자들이 수학의 군(group) 이론에서 분류 기준을 찾게 되었고, 이것이 입자물리학과 수학이 만나는 계기가 되었다."
    },
    {
      "question": "갈로아(Galois)가 군(group) 이론을 발전시킨 배경은?",
      "answer": "5차 방정식에 근의 공식이 존재하는지를 연구하는 과정에서였다. 2차~4차 방정식까지는 근의 공식이 존재하지만, 갈로아는 근의 속성을 그룹으로 분류하여 5차 이상 방정식에는 일반적 근의 공식이 존재하지 않음을 증명했다."
    },
    {
      "question": "아벨(Abel)의 수학적 업적은?",
      "answer": "5차 이상 다항식 방정식에는 일반적인 근의 공식이 존재하지 않는다는 것을 최초로 수학적으로 증명했다. 노르웨이 출신으로 20대에 요절했지만, 현대 입자물리학의 수학적 아버지로 평가된다."
    },
    {
      "question": "리(Lie)의 대칭군이 입자물리학에서 어떻게 활용되는가?",
      "answer": "리가 발전시킨 대칭군(Lie group) 이론은 소입자를 분류하는 수학적 근거가 되었다. 표준 모형의 $SU(3) \\times SU(2) \\times U(1)$ 게이지 대칭이 모두 리군으로 표현된다."
    },
    {
      "question": "우주의 네 가지 기본 힘과 대칭군의 관계는?",
      "answer": "중력을 제외한 세 가지 힘이 대칭군으로 표현된다. $U(1)$은 전자기력, $SU(2)$는 약력(약한 상호작용), $SU(3)$는 강력(강한 상호작용, 쿼크 간 힘)에 대응한다."
    },
    {
      "question": "입자물리학에서 '대칭'이 중요한 이유는?",
      "answer": "대칭이 우주의 근본 원리이기 때문이다. 우주의 기본 힘들이 대칭군으로 기술되며, 우주의 존재 자체가 '자발적 대칭 깨짐(Spontaneous Broken Symmetry)'으로 설명된다."
    },
    {
      "question": "자발적 대칭 깨짐(Spontaneous Broken Symmetry)이란?",
      "answer": "원래 완전한 대칭 상태에 있던 것이 저절로(자발적으로) 대칭이 깨지면서 현재의 우주가 탄생했다는 개념이다. 즉, '우주의 존재 = 대칭의 깨짐'이다."
    },
    {
      "question": "아벨과 리의 수학이 양자 컴퓨팅과 어떤 관련이 있는가?",
      "answer": "아벨과 리의 수학적 업적은 현대 양자 컴퓨팅을 이해하는 출발점이 된다. 양자 컴퓨팅의 기반이 되는 양자역학과 입자물리학의 수학적 토대를 이 두 사람이 마련했기 때문이다."
    },
    {
      "question": "이휘소 박사는 입자물리학에서 어떤 역할을 했는가?",
      "answer": "1960~70년대 입자물리학의 붐 시기에 맹활약한 한국 출신 물리학자이다. 가속기에서 쏟아져 나오는 소입자 연구에 중요한 기여를 했다."
    },
    {
      "question": "$E=mc^2$이 입자 가속기 실험에서 어떻게 적용되는가?",
      "answer": "빛에 준하는 속도로 가속된 입자들의 운동 에너지가 충돌 시 $E=mc^2$에 의해 질량으로 전환되어 새로운 입자들이 탄생한다. 이것이 자연 상태에선 존재하지 않던 수천 개의 새로운 입자가 생성되는 원리이다."
    },
    {
      "question": "CERN(유럽 입자 물리 연구소)에서 하는 실험은?",
      "answer": "양성자와 반양성자를 빛의 속도의 90% 이상으로 가속하여 정면 충돌시킨다. 충돌 시 가속 에너지가 질량으로 전환되어 수천 개의 새로운 입자가 생성되며, 이를 분석하여 물질의 근본 구조를 연구한다."
    },
    {
      "question": "원자 모델, 방사선, 수학 이론의 세 흐름이 통합된 과정을 요약하면?",
      "answer": "① 영국에서 원자 모델(원자핵+전자)을 실험으로 완성 ② 프랑스에서 방사선을 발견하고 핵 변환을 이해 ③ 가속기에서 수천 개 새 입자가 발견되자 노르웨이·프랑스 수학자들의 군 이론(대칭군)으로 분류. 세 독립 흐름이 결합하여 입자물리학의 표준 모형이 탄생했다."
    },
    {
      "question": "방사선 연구의 역사적 흐름을 정리하면?",
      "answer": "야금학자들이 광물에서 방사선 발견 → 베크렐의 감광지 실험 → 뢴트겐의 X선 발견(1901 노벨상) → 퀴리 부부의 우라늄 농축 → 방사선이 원자 핵에서 나온다는 것 확인 → 알파·베타·감마선 분류 → 베타선=전자 확인 → 핵 변환 이해."
    },
    {
      "question": "스웨덴·노르웨이 지역의 지구과학적 특징은?",
      "answer": "빙하기와 직접 관련된 지역으로, 빙하시대를 실제로 볼 수 있는 지질학적 현장이다. 또한 근대 주기율표가 만들어지는 과정을 총체적으로 학습할 수 있는 지역이기도 하다."
    },
    {
      "question": "멘델레예프와 주기율표의 관계는?",
      "answer": "주기율표를 만든 사람은 러시아의 멘델레예프이다. 그러나 주기율표의 희토류 원소 10여 개는 스웨덴의 한 마을에서 시작되어 발견되었으므로, 주기율표 완성 과정에서 스웨덴이 핵심적 역할을 했다."
    },
    {
      "question": "발트 3국과 북유럽을 통해 러시아 역사를 이해할 수 있는 이유는?",
      "answer": "스웨덴과 러시아 간의 북방 전쟁(약 10차에 걸친 대규모 전쟁)이 있었고, 발트 3국도 이 전쟁사와 밀접하다. 이를 통해 러시아 역사를 다른 측면에서 조망할 수 있으며, 스칸디나비아 사회복지 국가의 출현 배경도 이해할 수 있다."
    }
  ]
}