{
  "version": 1,
  "items": [
    {
      "question": "디테일링 중독의 증상은 무엇인가?",
      "answer": "운전 중 세차장이 한가한 것을 보면 가고 싶은 욕구가 생기고, 더러운 차를 보면 세차해주고 싶어하며, 해장으로 세차를 할 정도로 강렬한 욕구를 느낀다."
    },
    {
      "question": "디테일링을 하는 사람들이 차 문을 여는 방식은 일반인과 어떻게 다른가?",
      "answer": "손 지문이 남지 않도록 손등으로 문을 닫거나, 손잡이만 잡고 타고 내리도록 동승자에게 설명한다. 심지어 신발을 벗고 타야 하는지 물어보기도 한다."
    },
    {
      "question": "다른 사람이 볼 때와 디테일러가 볼 때 차의 상태는 어떻게 다른가?",
      "answer": "일반인은 그냥 '깨끗하다'고만 느끼지만, 디테일러는 '마음의 눈'으로 광택의 수준, 틈새의 청결도, 코팅 상태 등을 세밀하게 구분해서 본다."
    },
    {
      "question": "현대 세차장의 시설은 어떻게 발전했는가?",
      "answer": "프랜차이즈화되어 깔끔한 실내 공간, 게러지형 개별 공간, 히터와 에어컨이 있는 사계절 이용 가능한 시설이 등장했다. 에어건, 진공청소기 등 다양한 장비를 제공한다."
    },
    {
      "question": "게러지형 세차장의 특징은 무엇인가?",
      "answer": "한 대의 차만 들어갈 수 있는 독립 공간으로, 물 청소와 드라잉을 모두 할 수 있다. 디테일링처럼 오래 걸리는 작업을 할 때 다른 사람 눈치를 보지 않아도 된다."
    },
    {
      "question": "디테일링 세차장 이용 비용은 얼마인가?",
      "answer": "시간당 13,000원에서 20,000원 정도이며, 회원권을 끊으면 할인을 받을 수 있다. 5시간 정도 하면 6-7만 원 정도 나오지만 결과물의 만족도는 손세차 맡긴 것과 비교할 수 없다."
    },
    {
      "question": "디테일링 초보자가 준비해야 할 기본 장비는 무엇인가?",
      "answer": "버킷(바게스), 미트, 카샴푸, 드라잉 타월(극세사), 왁스, 왁스용 타월 정도면 충분하다. 초보자 세트로 판매되는 제품을 구매하는 것이 좋다."
    },
    {
      "question": "디테일링 초보자가 첫 시도에서 겪는 어려움은 무엇인가?",
      "answer": "바퀴 4개만 닦아도 체력이 소진될 정도로 힘들고 노동처럼 느껴진다. 영상에서는 쉬워 보이지만 실제로는 몸에 적응하기까지 시간이 필요하다."
    },
    {
      "question": "디테일링을 취미로 계속하는 사람과 포기하는 사람의 차이는 무엇인가?",
      "answer": "보통 세 번 정도 시도 후 결정된다. 힘들어도 결과물을 보고 뿌듯함과 쾌감을 느끼면 계속하게 되고, 그렇지 않으면 손을 놓게 된다."
    },
    {
      "question": "디테일링 초보자에게 주는 조언은 무엇인가?",
      "answer": "처음부터 많은 장비를 사지 말고, 눈에 보이는 부위만 깨끗이 하라. 휠 안쪽 같은 보이지 않는 곳은 나중에 하고, 가벼운 마음으로 시작하는 것이 좋다."
    },
    {
      "question": "여성 초보자가 세차장에 대해 느끼는 두려움은 무엇인가?",
      "answer": "기계가 크고 소리가 시끄러우며, 남자 아저씨들만 있을 것 같아 무섭게 느껴진다. 하지만 실제로는 아무도 신경 쓰지 않으므로 눈치 보지 말고 자신 있게 하면 된다."
    },
    {
      "question": "디테일링을 업으로 전환할 수 있는가?",
      "answer": "가능하다. 취미로 하다가 업으로 전향하는 사람이 많다. 발수 코팅만 해도 업체에서는 10만 원을 받지만, 기술과 약제가 있으면 30-40분이면 끝나므로 수익이 된다."
    },
    {
      "question": "디테일링 동호회의 역할은 무엇인가?",
      "answer": "같이 세차하는 팀으로, 단톡방에서 세차장 상황을 공유하고 신규 멤버에게 조언한다. 세차장 혼잡도를 미리 확인해 민폐를 주지 않도록 배려한다."
    },
    {
      "question": "디테일링을 하면서 콜렉팅의 재미를 느끼는 이유는 무엇인가?",
      "answer": "브랜드마다 라벨 디자인이 다른 용품을 전부 수집해 같은 디자인으로 진열하면 만족감이 크다. 한정판을 포함해 브랜드를 섭렵하는 것도 즐거움 중 하나다."
    },
    {
      "question": "극세사 타월의 종류와 특징은 무엇인가?",
      "answer": "폴리에스터와 폴리아미드의 혼용 비율에 따라 부드러움이 다르다. 드라잉 타월은 플러피형(털이 빠짐)과 트위스트형(물을 잘 먹음) 등 용도별로 다양하다."
    },
    {
      "question": "디테일러들이 자신만의 '최애 제품'을 갖는 이유는 무엇인가?",
      "answer": "여러 제품을 사용해보면서 자신의 루틴과 손에 맞는 장비, 선호하는 약품이 정해진다. 이를 통해 자신만의 스타일과 방법을 확립하게 된다."
    }
  ]
}