{
  "version": 1,
  "items": [
    {
      "question": "모기에 물렸을 때 가려운 이유는?",
      "answer": "모기가 흡혈 시 혈액 응고를 막는 항응혈성 타액을 주입한다. 이 타액이 체내에서 만들어지지 않는 이물질(단백질)이라 면역 반응이 일어나 히스타민이 분비되고, 이것이 가려움증과 붓기를 유발한다."
    },
    {
      "question": "모기가 주입하는 타액의 성분과 의학적 활용 가능성은?",
      "answer": "혈액 응고를 막는 항응혈성 물질이다. 일본에서는 혈전 치료제 연구에 이 성분을 활용하기도 했다. 병원에서 채혈 시 쓰는 EDTA와 유사한 원리로 작동한다."
    },
    {
      "question": "모기 암컷과 수컷의 차이점은?",
      "answer": "암컷만 흡혈하고, 수컷은 흡혈하지 않으며 식물의 과즙 등 당분을 섭취한다. 암컷은 평생 한 번만 교미하고, 수컷은 여러 번 교미할 수 있으나 영양 보충이 어려워 일주일~열흘 정도로 수명이 짧다."
    },
    {
      "question": "모기 암컷이 흡혈을 반드시 해야 하는 이유는?",
      "answer": "혈액 속의 단백질 성분(적혈구 포함)을 섭취해야 알을 만들 수 있기 때문이다. 흡혈 후 5일간 난발육을 거쳐 알을 낳는다."
    },
    {
      "question": "모기 암컷의 교미 및 산란 과정은?",
      "answer": "암컷은 평생 한 번 교미하며, 수컷의 정충을 수정낭(사랑의 열매 모양의 3개 기관)에 보관한다. 이후 흡혈하고 5일간 난발육 후 한 번에 최대 250개의 알을 낳는다."
    },
    {
      "question": "모기 한 마리가 네 세대를 거치면 개체 수가 얼마나 되는가?",
      "answer": "약 1억 마리가 된다."
    },
    {
      "question": "모기가 발바닥이나 발을 자주 무는 이유는?",
      "answer": "발에 땀이 많은 사람은 발 냄새가 심한데, 이 숙성된 땀 성분의 냄새를 모기가 매우 좋아하기 때문이다."
    },
    {
      "question": "파리가 손발을 비비는 행동의 이유는?",
      "answer": "파리 몸의 털은 감각 기관인데, 먼지 등이 묻으면 감각이 둔해진다. 따라서 항상 몸을 깨끗이 청소해 감각을 유지하기 위해 비비는 행동을 한다."
    },
    {
      "question": "전 세계 파리의 종류와 역할은?",
      "answer": "전 세계적으로 약 14만 종이 있으며 161개 과로 나뉜다. 해충(병균 매개, 농작물 피해)도 있고 익충(분해자, 화분 매개)도 있다."
    },
    {
      "question": "파리가 생태계에서 수행하는 두 가지 주요 역할은?",
      "answer": "첫째, 분해자 역할로 사체나 쓰레기를 유충(구더기)이 먹어 분해한다. 둘째, 화분 매개(꽃가루받이) 역할로, 자연 생태계에서 벌보다 파리가 더 중요한 수분 역할을 한다."
    },
    {
      "question": "피를 빠는 파리의 종류에는 무엇이 있는가?",
      "answer": "등에(소 등에 붙어 피를 빠는 종), 이파리(다양한 동물에 기생하는 종), 침집파리(소에 럼피스킨 병을 옮기는 종) 등이 있다. 모기도 파리 목에 속하므로 파리 중 흡혈하는 종은 생각보다 많다."
    },
    {
      "question": "과실파리가 농산물 교역에서 중요한 이유와 칠레 과일이 수입되는 이유는?",
      "answer": "과실파리는 사과, 호박, 오이 등에 알을 낳아 수확을 불가능하게 한다. 칠레는 안데스 산맥 덕분에 과실파리가 분포하지 않는 청정 지역이기 때문에 세계적으로 과일 수출에 유리하고 한국에도 수입된다."
    },
    {
      "question": "한국 외국산 사과 수입이 어려운 이유는?",
      "answer": "사과를 공격하는 과실파리가 분포하는 국가의 사과를 수입할 경우, 과실파리가 국내에 정착해 피해가 발생할 수 있기 때문이다. 과실파리 유무가 농산물 교역에서 매우 중요하다."
    },
    {
      "question": "파리 수컷의 생애 주기와 특징은?",
      "answer": "파리 수컷은 교미를 위한 존재로, 교미 후 대부분 죽거나 암컷에게 잡아먹힌다. 일부 종(춘파리 등)은 암컷이 교미 중 혹은 교미 후 수컷을 먹어버린다. 수컷들은 암컷을 유혹하기 위해 혼인 비행 시 먹이를 가져다 바치기도 한다."
    },
    {
      "question": "파리의 비행 능력이 뛰어난 이유는?",
      "answer": "다른 곤충이 날개 두 쌍인 것과 달리 파리는 날개 한 쌍(앞날개)만으로 날고, 뒷날개는 평형 유지에 사용한다. 이 덕분에 정지 비행, 예각 비행, 후진 비행 등이 가능하며 최고 시속 400km로 날 수 있다."
    },
    {
      "question": "파리채로 파리를 잡는 것이 어려운 이유는?",
      "answer": "파리는 파리채를 내리치려는 순간 이미 이를 감지하고 점프를 시작한다. 파리가 잡히는 것은 우연히 파리채 방향으로 날아간 경우이며, 파리의 비행 능력과 반응 속도가 매우 뛰어나기 때문이다."
    }
  ]
}