{
  "version": 1,
  "items": [
    {
      "question": "피드가 잉크를 너무 많이 머금으면 어떤 문제가 생기나?",
      "answer": "피드가 잉크를 과도하게 머금으면 잉크가 있어도 펜촉으로 잉크가 나오지 않는 문제가 발생한다. 일본의 일부 만년필이 이런 경우에 해당하며, 피드의 크기가 펜촉보다 지나치게 크면 밸런스가 무너진다."
    },
    {
      "question": "슈미트 피드의 가장 두드러진 특징은 무엇인가?",
      "answer": "슈미트 피드는 열에 의한 변형이 거의 없어 100개를 서로 바꿔 껴도 모두 맞을 정도로 정교하다. 박종진 소장은 만 개 이상의 피드를 직접 검사하며 '세계 3대 피드 안에 들어간다'고 평가했다."
    },
    {
      "question": "피드 품질이 만년필에서 중요한 이유는 무엇인가?",
      "answer": "피드가 나쁘면 쓸 때마다 잉크가 말라 있거나, 펜을 털면 잉크가 앞으로 튀어나오는 등 필기 자체가 불안정해진다. 아무리 외관이 아름다운 만년필도 피드가 좋지 않으면 실용성이 크게 떨어진다."
    },
    {
      "question": "워터맨이 1900년대 초반 만년필 시장에서 차지한 점유율은?",
      "answer": "워터맨은 1900년대 초반 만년필 시장에서 약 80%의 점유율을 차지했다. 피드 혁신이 시장 지배의 핵심 원인이었으며, 이후 파카 등 경쟁사들도 피드 개선에 주력하게 된다."
    },
    {
      "question": "피드의 발전이 만년필 뚜껑 디자인에 미친 영향은?",
      "answer": "피드가 커지면서 펜촉도 커지고, 펜촉이 커지면서 이를 덮는 뚜껑도 커지게 되었다. 뚜껑이 커지자 디자인 요소를 더 넣을 수 있게 되어 클립, 장식 등이 추가되고, 스크류 방식의 뚜껑도 등장했다."
    },
    {
      "question": "100화 기념 파우치의 품질에 대한 평가는?",
      "answer": "박종진 소장은 100화 파우치를 '세계 최고 수준'이라고 평가했다. 비단 같은 가죽 소재, 은 단추의 정밀한 간격, 완벽한 마감 등이 100만원 급의 품질이라고 극찬했다."
    },
    {
      "question": "몽블랑 파인라이너와 100화 파인라이너의 차이점은?",
      "answer": "몽블랑이 80만원에 판매하는 파인라이너의 내부에는 슈미트 부품이 들어 있다. 100화에서는 같은 슈미트 부품을 사용하면서도 약 8만원에 출시할 예정이다."
    },
    {
      "question": "슈미트 파인라이너의 필기 특징은 무엇인가?",
      "answer": "슈미트 파인라이너는 누르면 살짝 들어가는 텐션이 있으며 선이 번지지 않는 특성을 가지고 있다. 박종진 소장은 '만년필 다음 버전의 필기구'라고 표현할 만큼 필기감이 뛰어나다고 평가했다."
    },
    {
      "question": "세종 만년필의 특징은 무엇인가?",
      "answer": "세종 만년필은 금속 몸체에 6호 펜촉, 피스톤 필러를 갖춘 고급 만년필이다. 검정·빨간색 조합으로 화려하며, 100화 만년필보다 더 세련되고 섹시한 디자인이라는 평가를 받는다."
    },
    {
      "question": "이태준 선생이 서양 만년필을 선호한 이유 네 가지는?",
      "answer": "①필기 촉감이 좋고 오래 간다(이리듐 품질), ②잉크가 고르게 나온다(피드 품질), ③몸통이 튼튼하다, ④바다를 건너온 정감이 있다. 그는 다른 것은 아껴도 만년필에는 흥청망청 투자할 정도로 만년필을 애호했다."
    },
    {
      "question": "김소운 수필가와 콩클린 만년필의 이야기는 무엇인가?",
      "answer": "김소운 수필가는 스승에게 콩클린 만년필을 받았고, 1940년대 겨울 만주로 떠나는 유치환 선생에게 이별 선물로 그 콩클린을 건넸다. '파카나 워터맨은 명함도 못 내민다'는 스승의 말을 믿고 최고의 선물로 줬으나, 실제 콩클린의 품질은 그 정도가 아니었다."
    },
    {
      "question": "김소운이 유치환에게 콩클린을 선물할 때 한 설명은?",
      "answer": "김소운은 '콩클린이라고 좋은 거야, 파카나 워터맨은 명함도 못 내밀어, 한 6원 하는 건데 일본에도 몇 개 없다'고 설명했다. 하지만 이 설명은 스승에게 들은 과장된 말이었다."
    },
    {
      "question": "김소운의 콩클린 만년필이 결국 어떻게 됐나?",
      "answer": "유치환 선생이 쓰다가 고무 튜브가 터지자 김소운에게 고쳐달라고 돌려줬다. 김소운이 수리한 뒤 돌려주러 가다가 소매치기를 당해 잃어버렸고, 이 이야기를 '청자색 콩클린 만년필'을 보면 생각난다는 수필로 남겼다."
    },
    {
      "question": "콩클린 만년필의 실제 품질과 위상은 어떠했나?",
      "answer": "콩클린은 초창기(1900년대 초)에는 워터맨을 위협할 정도로 개성 있는 제품을 만들었으나, 1930년대 말부터 급격히 쇠퇴하여 1940년대에 사실상 소멸했다. 파카나 워터맨과 비교하면 실제 품질은 낮았으며, 김소운 수필의 스승이 뻥을 친 것이었다."
    },
    {
      "question": "현대에 부활한 콩클린 만년필의 문제점은 무엇인가?",
      "answer": "현대 콩클린은 옛날 필러 방식(크레센트 필러)과 현대 복잡한 피드 시스템이 서로 맞지 않아 잉크 공급이 원활하지 않다. 또한 원래 비율과 달리 불필요하게 크게 만들어져 밸런스가 맞지 않고 족보를 알 수 없는 디자인이라는 평가를 받는다."
    }
  ]
}