{
  "version": 1,
  "items": [
    {
      "question": "「돌리 모음곡」의 자장가는 어떤 특징이 있나요?",
      "answer": "영국인들이 가장 좋아하는 자장가로 알려져 있으며, 라디오 방송 시그널 음악으로도 사용되었습니다. 굉장히 잔잔하고 말랑말랑한 선율이 특징입니다."
    },
    {
      "question": "포레의 「달빛(Clair de lune)」 가곡은 어떤 배경으로 만들어졌나요?",
      "answer": "시인 폴 베를렌의 시에서 영감을 받아 만든 가곡입니다. 드뷔시도 같은 시인의 같은 주제로 피아노 음악을 만들었으며, 두 곡의 제목이 같습니다. 코메디아 델 아르테(광대극)의 애환을 담고 있습니다."
    },
    {
      "question": "포레의 달빛 가사의 핵심 내용은 무엇인가요?",
      "answer": "달빛 아래 가면을 쓴 광대들이 류트를 연주하며 춤추지만, 그들 자신은 행복을 믿지 않는 것 같다는 내용입니다. 슬픔과 기쁨이 교차하며, '고요하지만 아름답고 또한 슬프기도 한 달빛'으로 표현됩니다."
    },
    {
      "question": "폴 베를렌은 누구이며, 포레 음악과 어떤 관련이 있나요?",
      "answer": "19세기 프랑스 상징주의 시인으로, 랭보와의 폭발적인 동성 연애로도 유명합니다. 베를렌의 시는 포레의 「달빛」, 「감옥」 등 여러 가곡의 가사로 사용되었으며, 드뷔시의 음악에도 영감을 주었습니다."
    },
    {
      "question": "포레의 「감옥(Prison)」 가곡의 배경은 무엇인가요?",
      "answer": "폴 베를렌이 랭보와 다툼 끝에 총을 쏴 감옥에 갇힌 후, 자신의 처지를 돌아보며 쓴 시를 가사로 합니다. 감옥 창 너머 평범한 일상(푸른 하늘, 나무, 새소리)을 보며 젊은 날을 후회하는 심경을 담고 있습니다."
    },
    {
      "question": "포레의 「레퀴엠(Requiem)」은 어떤 특징이 있나요?",
      "answer": "역대 레퀴엠 중 가장 밝고 행복한 분위기의 레퀴엠으로, '내세의 행복'이라는 별칭이 있습니다. 죽음의 공포와 불안 대신 고통 없는 천국으로 넘어가는 열망을 담아, 장송곡임에도 희망적이고 아름답습니다."
    },
    {
      "question": "포레의 레퀴엠이 탄생한 특이한 사연은 무엇인가요?",
      "answer": "포레가 의뢰를 받은 것이 아니라 자신이 쓰고 싶어서 자발적으로 작곡한 작품입니다. 그러나 자신이 일하던 교회에서는 '새 곡이 필요 없다'고 했고, 출판업자도 대중성이 없다며 거절했습니다."
    },
    {
      "question": "포레가 마들렌 성당(Madeleine)과 가진 인연은 무엇인가요?",
      "answer": "포레는 파리 마들렌 성당의 오르가니스트로 오랫동안 활동했습니다. 어릴 때부터 수많은 장례식에서 레퀴엠을 연주한 경험이 그의 죽음관과 레퀴엠 작곡에 영향을 주었으며, 그의 장례식도 마들렌 성당에서 치러졌습니다."
    },
    {
      "question": "포레와 모차르트의 레퀴엠은 어떻게 다른가요?",
      "answer": "모차르트의 레퀴엠은 죽음의 공포와 불안, 구원에 대한 간절함이 직접적으로 느껴지는 반면, 포레의 레퀴엠은 죽음을 고통 없는 행복한 세계로의 전환으로 보아 밝고 희망적인 분위기를 지닙니다."
    },
    {
      "question": "포레가 '관객을 생각하지 않은 첫 번째 작곡가'라고 불리는 이유는 무엇인가요?",
      "answer": "생상스 등 당대 작곡가들은 곡이 팔려야 하므로 대중을 겨냥해 작곡했지만, 포레는 그것과 무관하게 자신의 음악적 목소리를 유지했습니다. 이는 제자들에게 '네 목소리를 내도 된다'는 메시지가 되어 드뷔시·라벨의 인상주의가 꽃피는 토대가 되었습니다."
    },
    {
      "question": "포레가 음악사에서 이룬 '조용한 혁명'은 무엇인가요?",
      "answer": "대중성을 의식하지 않고 자신만의 선율을 추구하며 현대 음악의 초석을 다진 것입니다. 파리 음악원 개혁을 통한 제도적 혁신, 그리고 레퀴엠에서 죽음을 공포가 아닌 행복으로 표현한 것도 조용한 혁명으로 평가됩니다."
    },
    {
      "question": "포레의 음악적 특징은 무엇인가요?",
      "answer": "굉장히 멜로디컬하고 잔잔한 선율이 특징이며, 타악기 등 악기 효과(오케스트레이션)를 중시하지 않아 심심하게 들릴 수 있습니다. 선율 라인을 연구하지 않으면 심심하게 느껴지지만, 인상주의의 씨앗이 되는 모호하고 몽환적인 화성을 담고 있습니다."
    },
    {
      "question": "포레가 제자들을 가르친 방식은 어떤 점에서 특별했나요?",
      "answer": "제자들의 음악성을 건드리지 않고 각자의 스타일을 유지하도록 격려했습니다. 그 결과 그의 제자들은 성향이 모두 달랐으며, 이것이 드뷔시·라벨 등 다양한 인상주의 음악가를 배출한 원동력이 되었습니다."
    },
    {
      "question": "포레의 제자 라벨은 포레에게 어떤 영향을 주었나요?",
      "answer": "라벨은 자신의 현악사중주를 포레에게 헌정하며 스승에게도 사중주를 써보라고 권했습니다. 포레는 말년에 청력을 잃어가면서 제자의 권유로 현악사중주를 작곡했고, 이 작품은 완전한 현대 음악으로 변모했습니다."
    },
    {
      "question": "포레의 청력 상실과 말년의 작곡 활동은 어떠했나요?",
      "answer": "포레는 말년에 청력을 완전히 잃었습니다. 국가에서 그를 위한 음악회를 열었지만 본인은 한 음도 듣지 못했으며, 청력을 잃은 상태에서도 완전한 현대 음악인 현악사중주를 완성했습니다."
    }
  ]
}