{
  "version": 1,
  "items": [
    {
      "question": "인간을 규정하는 가장 중요한 특질은 무엇인가?",
      "answer": "느낌이다. 느낌은 감정, 의식, 기억, 생각 등 정신 현상을 포괄적으로 담을 수 있으며, 인간과 대상을 만났을 때 확 덮쳐오는 것이다."
    },
    {
      "question": "동물의 감각과 인간의 느낌은 어떻게 다른가?",
      "answer": "감각과 느낌은 완전히 다르다. 동물은 감각 수준에 머물지만, 인간의 느낌은 대뇌 피질 전체가 관여하는 고도의 정신작용이다. 개나 고양이도 느낌 차원까지 올라오지 못했다."
    },
    {
      "question": "느낌을 구성하는 5가지 요소는 무엇인가?",
      "answer": "1) 감각 입력 처리, 2) 생존 반응, 3) 신체 피드백, 4) 대뇌피질의 각성 상태, 5) 기억. 이 중 기억이 느낌의 약 70~80%를 차지하며 가장 중요하다."
    },
    {
      "question": "느낌의 구성 요소들은 시대와 상황에 따라 어떻게 달라지는가?",
      "answer": "다섯 가지 요소의 가중치가 시대별로 다르다. 사회가 안정되고 시간이 흐르면 기억이 중요해지고, 야생 환경에 가까워지면 생존 반응과 공포 반응이 중요해진다."
    },
    {
      "question": "사람이 사람의 얼굴을 보고 느낌이 안 생기면 어떻게 되는가?",
      "answer": "그 사람은 사회생활을 할 수 없다. 실제로 SF 소설에서 진짜 사람과 인조인간을 구별하는 방법이 얼굴을 봤을 때 느낌이 생기는지 확인하는 것이다."
    },
    {
      "question": "느낌과 의식의 공통점은 무엇인가?",
      "answer": "주의(어텐션)를 하지 않아도 자동으로 일어난다는 점이다. 기억은 주의를 해야 기억으로 넘어가지만, 느낌과 의식은 내 의지와 상관없이 자동으로 발생한다."
    },
    {
      "question": "'미각의 절반은 기억이다'라는 말의 의미는 무엇인가?",
      "answer": "음식의 맛은 단순한 미각이 아니라 그와 연결된 기억이 절반 이상을 차지한다. 임종 무렵 어릴 때 먹었던 음식이 생각나는 것도 기억 때문이다."
    },
    {
      "question": "인간의 정신작용을 구성하는 가장 작은 단위는 무엇인가?",
      "answer": "이미지다. 물질의 원자에 해당하는 것이 정신작용에서는 이미지이며, 시각 이미지, 청각 이미지, 촉각 이미지 등이 있다."
    },
    {
      "question": "시각 이미지는 어떤 세 가지 요소로 구성되는가?",
      "answer": "색깔, 형태, 움직임이다. 이 세 가지는 각각 다른 영역에서 처리된 후 하측두엽에서 결합되어 하나의 시각 이미지를 만든다."
    },
    {
      "question": "시각 정보가 두 가지 경로로 나뉘는 이유는 무엇인가?",
      "answer": "뒤통수에서 귀 쪽(측두엽)으로 가는 경로는 색깔과 형태를 처리하고, 정수리로 가는 경로는 움직임을 처리한다. 정수리로 가는 움직임 정보는 손 움직임과 연결되어 빠른 반응을 가능하게 한다."
    },
    {
      "question": "시각과 운동이 결합하는 경로는 의식이 관여하는가?",
      "answer": "아니다. 정수리로 가는 시각-운동 결합 과정은 무의식적으로 처리된다. 빠른 속도가 필요할 때는 의식이 개입하지 않으며, 의식이 들어가면 속도가 떨어진다."
    },
    {
      "question": "운동선수들에게 '힘을 빼라'고 하는 이유는 무엇인가?",
      "answer": "의식적 사고를 하지 말라는 의미다. 의식이 개입하면 근육에 의도적 힘이 들어가 훈련된 실력이 나오지 않고 반응이 늦어진다."
    },
    {
      "question": "범주화란 무엇인가?",
      "answer": "개별 대상의 공통된 특징을 추출하여 일반화하는 과정이다. 예를 들어 다양한 사과를 보고 '둥글고, 빨갛고, 꼭지가 있는' 등의 공통 특징을 묶어내는 것이다."
    },
    {
      "question": "범주와 개념의 관계는 무엇인가?",
      "answer": "범주화된 대상의 속성이 개념이다. 범주가 그릇이라면 개념은 그 그릇에 담긴 액체에 해당한다. 둘은 분리되지 않고 항상 함께 간다."
    },
    {
      "question": "인간 문화의 본질은 무엇인가?",
      "answer": "개념을 공유하는 것이다. 개념 공유를 통해 집단 지향성이 생기고, 이것이 사회적 실재(법률, 정치 등)를 만들어낸다."
    },
    {
      "question": "일화기억(에피소딕 메모리)이란 무엇인가?",
      "answer": "이야기(에피소드) 단위로 저장되는 기억으로, 누구를 만났고 어디 갔고 무엇을 먹었는지 등의 경험 기억이다. 동물은 이 기억을 10분 정도밖에 유지하지 못하지만 인간은 30년 이상 유지할 수 있다."
    }
  ]
}