{
  "version": 1,
  "items": [
    {
      "question": "음소 인식(Phoneme Recognition) 다이애드의 역할과 기원은 무엇인가?",
      "answer": "오디오 스트림을 처리해 개별 음소(발성의 최소 구별 단위)를 식별한다. 이 다이애드의 When·What 모듈은 다른 포유류와 새의 마음에서 소리 순서를 식별하는 기존 청각 When·What 쌍에서 적응된 것으로 보인다."
    },
    {
      "question": "음절 인식(Syllable Recognition) 다이애드는 어떻게 작동하는가?",
      "answer": "음소 인식 다이애드가 보낸 각 음소(예: 'S', 'U')를 받아 음소 순서를 하나의 음절(예: 'SU')로 합성한다."
    },
    {
      "question": "단어 인식(Word Recognition) 다이애드는 어떻게 작동하며 언제 공명이 일어나는가?",
      "answer": "음절 인식 다이애드가 보낸 음절 순서(예: 'SU','PER','MIND')를 하나의 상향식 표상('SU-PER-MIND')으로 입력받아 기억 속 하향식 단어('SUPERMIND')와 대조한다. 일치하면 What 모듈에서 공명이 일어나 단어를 의식적으로 인식한다."
    },
    {
      "question": "'합성 감각질(synthesizing qualia)'이란 무엇인가?",
      "answer": "단어를 인식하는 경험으로, 뜻을 모르는 단어를 인식할 때도 경험한다. 예를 들어 낯선 음절 패턴 'brabble'이 제대로 형성된 단어임을 인식하는 것도 합성 감각질의 예이다."
    },
    {
      "question": "언어 스택의 각 다이애드에서 When 모듈과 What 모듈은 어떤 수준의 언어를 처리하는가?",
      "answer": "When 모듈은 짝을 이루는 What 모듈보다 낮은 수준을 처리한다. 예를 들어 음절 인식 다이애드의 When 모듈은 음소 순서를 합성하고, 짝인 What 모듈은 그 순서로 형성된 음절을 인식한다."
    },
    {
      "question": "저자는 언어가 도약한 시점을 언어 스택에 무엇을 추가했을 때로 보는가?",
      "answer": "매우 강력한 When-What 쌍인 문장 인식(Sentence Recognition) 다이애드를 언어 스택에 추가했을 때이다."
    },
    {
      "question": "언어 스택에서 '뒤로 가는 시간 사고(backward-in-time thinking)'와 언어적 소통을 가능케 한 연결성은 무엇인가?",
      "answer": "각 언어 다이애드를 바로 아래 다이애드로 다시 연결하는 '피드백(feedback) 연결'이다. 상위 다이애드가 하위 다이애드에 맥락 정보를 보내 하위 다이애드가 언어 인식을 개선하도록 돕는다."
    },
    {
      "question": "피드백 연결 설계 원리가 만드는 강력한 예측은 무엇인가?",
      "answer": "언어 스택의 모든 수준이 각자 고유한 '뒤로 가는 시간 지각'의 착시를 나타낼 것이라는 예측이다. 실제로 이것이 사실이다."
    },
    {
      "question": "'DELIVERY(딜리버리)' 착시 실험은 무엇을 보여주는가?",
      "answer": "'VER'의 'V' 소리를 백색소음으로 대체해도 청자는 배경 소음과 함께 또렷한 'V' 소리를 듣는다. 이는 단어 인식 다이애드가 피드백을 보내 음절 인식 다이애드에 소음 음절을 'VER'로 대체하라고 알려주기 때문이다."
    },
    {
      "question": "'DELIVERY'와 'DELIBERATE' 실험을 함께 비교하면 무엇을 알 수 있는가?",
      "answer": "같은 앞 음절('DE','LI')과 소음이 주어져도, 'DELI*ERY'에서는 'V'로, 'DELI*ERATE'에서는 'B'로 들린다. 소음에 가려진 음절은 뒤따르는 음절을 처리한 '후에' 대체되므로, 언어 이해는 시간 여행을 포함한다."
    },
    {
      "question": "음소 인식 다이애드와 청각 장면 모듈 사이에서 나타나는 뒤로 가는 시간 착시의 예는 무엇인가?",
      "answer": "연속 음소('EEEEEE')가 소음에 잠깐 끊겨도('EEEE**EEEE') 우리는 배경 소음 위 하나의 끊김 없는 음소로 듣는다. 시각 장면 모듈이 끊긴 선을 채우는 것과 유사하게 소리의 틈을 뒤로 채운다."
    },
    {
      "question": "'EEEE**'(음소-소음-침묵) 실험은 소음 채우기에 대해 무엇을 증명하는가?",
      "answer": "이 경우 소음 위의 음소가 아니라 음소 '다음에' 소음이 들린다. 음소 인식 다이애드는 소음 '이후'의 소리를 처리하기 전까지는 소음을 채울지 알 수 없음을 보여준다."
    },
    {
      "question": "동음이의어(homophone) 처리에서 뒤로 가는 시간 사고는 어떻게 작동하는가?",
      "answer": "단어 인식과 문장 인식 다이애드 사이에서 작동한다. 예: 'The scent of the two-cent stamp sent me back'에서 문장 인식 다이애드가 문장을 인식한 후 단어 인식 다이애드에 scent, cent, sent의 구별된 정체성을 피드백으로 알려준다."
    },
    {
      "question": "스티븐 그로스버그의 수학이 가진 설명력의 의의는 무엇인가?",
      "answer": "소수의 방정식과 네트워크 구성 원리가 When-What 다이애드의 반복 구조와 다양한 언어 착시·효과를 설명하며, 언어에 특화된 새 방정식이나 원리를 요구하지 않는다. 같은 수학이 새 노래도 설명한다."
    },
    {
      "question": "명금류의 '새 노래 스택(birdsong stack)'은 무엇을 시사하는가?",
      "answer": "새의 마음도 When-What 다이애드의 스택을 가진 것으로 보인다. 새 노래도 계층적 수준(음표·음절·프레이즈·노래, 인간의 음소·음절·단어·문장에 대응)을 가지며 빠진 음표를 채운다. 즉 언어 스택조차 인간을 새와 구별하지 못한다."
    },
    {
      "question": "인간을 모든 모듈 마음 위로 끌어올린, 언어의 결정적 신경 구성 요소는 무엇을 제공하는가?",
      "answer": "'의미(meaning)'라는 의식적 충격을 제공하는 구성 요소이다. 새를 포함한 다른 마음과 인간을 구별하는 것은 바로 이 의미를 부여하는 능력이다."
    },
    {
      "question": "단어를 이해할 때 들어오는 '의미'의 경험이 단어 자체의 지각적 특성과 무관하다는 것은 무슨 뜻인가?",
      "answer": "예를 들어 'ice(얼음)'라는 청각 패턴 자체는 차갑거나 결정 구조를 가지지 않지만, 우리는 그 단어를 이해할 때 그런 의미를 생생히 경험한다. 즉 소리와 의미의 연결은 임의적이다."
    },
    {
      "question": "단어와 의미의 연결이 임의적이고 유연하다는 것을 보여주는 'bat'의 예는 무엇인가?",
      "answer": "'bat'은 야행성 나는 동물, 나무 방망이, 그리고 그 방망이로 무언가를 치는 행위를 뜻한다(단, 나는 동물로 치는 것은 아님). 오직 호모의 마음만이 단어와 의미를 쉽게, 본능적으로 연결한다."
    },
    {
      "question": "새의 마음은 새 노래의 무엇을 의식하고 무엇을 의식하지 못하는가?",
      "answer": "새는 새 노래의 음표, 음절, 프레이즈는 의식하지만, 그것들의 상징적 의미(symbolic meanings)는 의식하지 못한다."
    },
    {
      "question": "마음이 청각 패턴을 의미와 연결하는 방식은 무엇인가?",
      "answer": "단어를 감각질(qualia)에 연결한다. 구체적으로, 언어 스택 안에서 공명하는 언어적 표상이 의식 카르텔에서 공명하는 정신적 표상과 함께 공명한다."
    }
  ]
}