{
  "version": 1,
  "items": [
    {
      "question": "루벤스가 발명한 '오일 스케치' 기법은 무엇이며, 어떻게 활용했나?",
      "answer": "유화로 밑그림을 그려 제자들에게 주는 방식이다. 구성, 인물, 배경, 색깔을 모두 표시한 작은 유화 드로잉을 제공하면 제자들이 완성하고 루벤스가 마무리했다."
    },
    {
      "question": "루벤스는 작품 판매 시 가격을 어떻게 차등화했나?",
      "answer": "계약 시 루벤스가 직접 그린 비율을 명시했다. 100% 루벤스, 70% 루벤스, 30% 루벤스, 또는 제자 완성 후 마무리만 한 작품 등으로 구분해 가격을 달리했다."
    },
    {
      "question": "2016년 베스트스테인 교수가 발견한 결정적 증거는?",
      "answer": "친구의 개인 소장 화첩에서 루벤스 소묘와 동일한 인물의 그림을 발견했다. 1609년 출간된 데프리스의 화첩에 명나라 상인 이풍의 초상이 실려 있었다."
    },
    {
      "question": "화첩 속 인물과 루벤스 소묘의 일치점은?",
      "answer": "원통형 모자, 옷, 포즈(양손을 소매에 넣은 자세), 얼굴 용모(눈썹, 눈, 코, 입술), 신발, 귀 양쪽으로 날리는 뒷머리 등이 모두 동일하다."
    },
    {
      "question": "루벤스가 제단화의 동양인을 그릴 때 실제 모델이 아닌 그림을 참고했다는 증거는?",
      "answer": "1617년 제단화 주문을 받은 후, 1609년 출간된 화첩의 명나라 상인 이풍 그림을 발견해 그대로 베꼈다. 화첩이 루벤스가 로마를 떠난 1608년 이후 출간되었기 때문에 실물 모델일 수 없다."
    },
    {
      "question": "2011년 국립중앙박물관 초상화 전시에서 문제가 된 점은?",
      "answer": "루벤스 소묘 원작이 전시되어 곽차섭 교수가 실물을 볼 수 있었음에도, 테두리 선과 잘린 부분을 확인하고도 자신의 주장(조선인설)을 철회하지 않았다."
    },
    {
      "question": "노성두 박사의 저서 제목과 판매 상황은?",
      "answer": "『루벤스는 안토니오 코레아를 그리지 않았다』. 박사가 주장해서 이 제목으로 출간했으나 거의 팔리지 않아 절판조차 되지 않고 재고가 그대로 남아 있다."
    },
    {
      "question": "안트베르펜이 가톨릭 도시가 된 배경은?",
      "answer": "네덜란드 독립 당시 북쪽은 프로테스탄트로, 남쪽 플랑드르(현재 벨기에)는 가톨릭으로 분리되었다. 안트베르펜은 스페인 카를 5세에게 충성한 가톨릭 중심 도시였다."
    },
    {
      "question": "루벤스가 종이를 안정적으로 공급받을 수 있었던 이유는?",
      "answer": "루벤스의 아내 헬레나 푸르망의 남동생(처남)이 안트베르펜 제지 공장 사장이어서 공방에 종이를 지속적으로 공급받았다."
    },
    {
      "question": "루벤스의 자화상에서 모자를 쓴 이유는?",
      "answer": "30대부터 탈모가 진행되어 머리가 빠졌기 때문이다. 모자를 벗은 자화상은 단 한 점만 있으며, 그 그림에서는 탈모 진행 상태가 명확히 보인다."
    },
    {
      "question": "루벤스 소묘에 망건이 없다는 것이 중요한 이유는?",
      "answer": "조선에서는 방건을 쓸 때 반드시 이마의 기름을 막기 위해 밑에 망건(머리띠)을 두르는데, 루벤스 소묘에는 망건이 없다. 이는 조선 복식이 아니라는 추가 증거다."
    },
    {
      "question": "제단화 속 동양인이 입은 철릭의 색깔이 조선 복식이 아닌 이유는?",
      "answer": "황금색 철릭을 입고 있는데, 조선에서는 신분에 따라 철릭 색깔이 정해져 있었고 황금색은 임금님도 입을 수 없는 색이었다."
    }
  ]
}