{
  "version": 1,
  "items": [
    {
      "question": "크루즈 승무원의 일반적인 계약 기간과 근무 형태는 어떻게 됩니까?",
      "answer": "승무원은 보통 6개월에서 최대 10개월까지 배에서 생활하며 근무하고, 이후 약 2개월의 휴가를 갖습니다. 계약 기간 동안은 휴일 없이 주 7일 근무하는 것이 일반적입니다."
    },
    {
      "question": "크루즈 선내에서 선장(Captain)의 권한은 어느 정도입니까?",
      "answer": "선장의 권한은 절대적입니다. 선내의 모든 규칙을 결정하며, 기상 악화 시 항로 변경이나 기항지 취소 등 안전과 관련된 모든 최종 의사결정을 내립니다."
    },
    {
      "question": "크루즈 여행 시 식사 비용은 어떻게 처리됩니까?",
      "answer": "대부분의 식사는 크루즈 비용에 포함되어 있어 무료로 제공됩니다. 뷔페와 정찬 식당(코스 요리)을 무제한으로 이용할 수 있으며, 특별한 경험을 위한 일부 파인 다이닝 레스토랑만 유료로 운영됩니다."
    },
    {
      "question": "크루즈 내 '정찬 식당(Formal Restaurant)'과 '뷔페'의 차이점은 무엇입니까?",
      "answer": "뷔페는 원하는 시간에 자유롭게 음식을 가져다 먹는 곳이며, 정찬 식당은 지정된 좌석에서 웨이터에게 코스 요리를 주문하여 식사하는 곳입니다. 두 곳 모두 기본적으로 무료로 이용 가능합니다."
    },
    {
      "question": "해외 크루즈 선사에서 한국인 셰프를 선호하는 이유는 무엇입니까?",
      "answer": "한국인 셰프는 한식뿐만 아니라 중식, 일식, 양식 등 다양한 국가의 요리를 수준급으로 소화할 수 있는 능력이 있기 때문입니다. 반면 타 국가 셰프들은 자국 요리에만 특화된 경우가 많습니다."
    },
    {
      "question": "크루즈 내에서 인터넷(Wi-Fi) 사용은 가능합니까?",
      "answer": "사용 가능하지만 'Ship Wi-Fi'라고 하여 별도의 비용을 지불해야 하며 가격이 비싼 편입니다. 배가 공해상에 있을 때는 위성을 사용하므로 육지보다 속도가 느릴 수 있습니다."
    },
    {
      "question": "크루즈 여행 중 매일 발행되는 '선상 신문'의 역할은 무엇입니까?",
      "answer": "선상 신문은 다음 날의 기항지 정보, 날씨, 드레스 코드, 식당 운영 시간, 각종 공연 및 행사 일정 등을 상세히 안내합니다. 승객들은 이를 통해 하루 일정을 계획합니다."
    },
    {
      "question": "한국인 승객들의 주요 특징은 무엇입니까?",
      "answer": "음식을 매우 잘 즐기지만 성격이 급해 요구사항을 즉각적으로 표현하고 불만을 현장에서 바로 제기하는 편입니다. 그러나 질서를 지키거나 줄을 서는 문화는 매우 잘 정착되어 있습니다."
    },
    {
      "question": "중국인 승객과 일본인 승객의 특징적인 차이는 무엇입니까?",
      "answer": "중국인 승객은 음식에 대한 집착이 강해 줄을 서지 않고 무질서하게 음식을 가져가는 경향이 있습니다. 반면 일본인 승객은 조용하며, 불만이 있어도 현장보다는 나중에 데스크를 통해 조용히 컴플레인하는 편입니다."
    },
    {
      "question": "크루즈 전문가가 '지중해 크루즈'를 가장 추천하는 이유는 무엇입니까?",
      "answer": "가성비가 뛰어나고(1박당 약 100달러 선), 육로로 이동하기 힘든 여러 국가와 도시를 효율적으로 방문할 수 있기 때문입니다. 서부 및 동부 지중해의 다양한 문화와 역사를 체험하기에 최적입니다."
    },
    {
      "question": "크루즈 여행이 젊은 층에게도 적합한 이유는 무엇입니까?",
      "answer": "이동 수단과 숙박, 식사가 해결되므로 배낭여행보다 효율적이고 가성비가 좋을 수 있습니다. 특히 카리브해 노선 등은 저렴하고 파티 문화가 발달해 있어 20~30대에게 인기가 많습니다."
    },
    {
      "question": "태풍이나 기상 악화 시 크루즈는 어떻게 대처합니까?",
      "answer": "선박에는 흔들림을 방지하는 '스테빌라이저' 장치가 있어 중심을 잡아줍니다. 또한 태풍이 오면 무리해서 운항하지 않고 즉시 항로를 변경하여 안전한 곳으로 대피하는 것을 최우선으로 합니다."
    },
    {
      "question": "한-일 크루즈 노선에 대한 전문가와 셰프의 견해 차이는 무엇입니까?",
      "answer": "여행사 대표는 이국적인 '크루즈 판타지'를 충족시키기에 부족하다며 비추천하지만, 셰프는 한국인에게 익숙한 음식과 프로그램이 제공되어 편안하게 즐길 수 있다는 점에서 긍정적으로 평가합니다."
    },
    {
      "question": "크루즈 내 유료 레스토랑(Specialty Dining)을 이용하는 주된 목적은 무엇입니까?",
      "answer": "음식의 질적 차이보다는 특별한 날을 기념하거나, 붐비는 무료 식당을 피해 조용하고 고급스러운 분위기에서 서비스를 받기 위한 '경험'의 측면이 강합니다."
    },
    {
      "question": "알래스카 크루즈의 특징은 무엇입니까?",
      "answer": "육로로는 접근하기 힘든 글레이셔 베이(Glacier Bay) 국립공원 등을 방문하여 빙하가 무너지는 장관을 볼 수 있습니다. 대자연을 감상하며 조용히 휴식하려는 여행객에게 적합합니다."
    },
    {
      "question": "크루즈 내 의료 및 치안 시스템은 어떻게 갖춰져 있습니까?",
      "answer": "선내에는 의사와 간호사가 상주하는 의료 센터가 있으며, 경찰 역할을 하는 보안 요원과 구금 시설(Detention center)도 갖춰져 있어 하나의 작은 도시처럼 운영됩니다."
    },
    {
      "question": "싱가포르 출발 크루즈의 장점은 무엇입니까?",
      "answer": "한국에서 비교적 가깝고, 10만 톤급 이상의 대형 선박을 경험할 수 있습니다. 주로 말레이시아, 태국 등 동남아시아 국가들을 기항하며 5박 7일 정도의 일정으로 다녀오기 좋습니다."
    },
    {
      "question": "월드 크루즈(World Cruise)란 무엇입니까?",
      "answer": "약 3개월에서 6개월 동안 전 세계 주요 항구를 돌며 여행하는 장기 크루즈입니다. 비용은 수천만 원대에 달하지만, 장기간 숙식과 이동이 해결된다는 점에서 가성비가 나쁘지 않다는 평가도 있습니다."
    }
  ]
}