{
  "version": 1,
  "items": [
    {
      "question": "이미지 회로와 감정 회로가 결합하면 무엇이 만들어지는가?",
      "answer": "느낌이 만들어진다. 시각, 청각, 촉각 이미지 회로가 생존을 동반하는 감정 회로와 결합하여 느낌이라는 정신작용이 출현했다."
    },
    {
      "question": "인간이 타인의 얼굴 표정 속에서 산다는 의미는 무엇인가?",
      "answer": "감정 하이웨이를 타고 진화하면서 타인의 얼굴 표정에서 느낌을 즉각 읽어내는 능력이 생존에 핵심이 되었다. 그래서 인간은 얼굴 표정을 통해 정보와 정서를 교류하며 살아간다."
    },
    {
      "question": "얼굴은 왜 '정보의 광고판'인가?",
      "answer": "얼굴에는 엄청난 정보량이 표출된다. 눈꼬리가 조금만 달라져도 비웃는지 진짜 미소인지 금방 간파할 수 있으며, 상대가 나에게 도움이 되는지 해를 끼칠지를 판단할 수 있다."
    },
    {
      "question": "인간의 얼굴에서 털이 사라진 이유는 무엇인가?",
      "answer": "상대방의 표정을 읽어야 생존에 유리했기 때문이다. 얼굴과 손바닥은 몸 전체보다 색깔의 다양성이 3배나 높으며, 까만 눈동자, 붉은 입술, 하얀 이빨의 대비가 정보 전달에 중요하다."
    },
    {
      "question": "음성 언어가 수화보다 강력한 이유는 무엇인가?",
      "answer": "발음은 액센트를 통해 감정 회로와 결합할 수 있다. 수화는 정보 전달은 가능하지만 정서를 교류하기 어렵다. 음성 언어는 정보와 느낌을 동시에 전달한다."
    },
    {
      "question": "'말이 통한다'는 표현의 진정한 의미는 무엇인가?",
      "answer": "정서가 통한다는 의미다. 말이 감정 회로와 결합되어 있기 때문에, 말이 통한다는 것은 느낌을 대규모로 공유할 수 있다는 뜻이다."
    },
    {
      "question": "몸의 털과 물통의 상관관계는 무엇인가?",
      "answer": "물통을 만드는 기술 문화가 먼저 출현하고, 그 후 인간의 털이 사라졌다. 정오의 뜨거운 날씨에 3시간 사냥하려면 땀으로 체온 조절을 해야 하는데, 털이 있으면 불가능하고 물 공급이 필수적이다."
    },
    {
      "question": "인간이 지구상에서 가장 많은 땀샘을 가진 이유는 무엇인가?",
      "answer": "장시간 사냥을 위해 체온 조절이 필수적이었기 때문이다. 땀을 분출하면 수분이 급격히 빠져나가므로 물통이 필요했고, 이 기술 문화와 함께 공진화했다."
    },
    {
      "question": "뇌와 문화의 공진화란 무엇인가?",
      "answer": "기술 문화(물통)와 인간의 형질(털 소실)이 서로 영향을 주고받으며 함께 진화하는 것이다. 뇌 단독이 아니라 문화와 함께 변화하는 과정이 공진화다."
    },
    {
      "question": "셀프 도메스티케이션(self-domestication)이란 무엇인가?",
      "answer": "스스로 길들여지는 과정이다. 인간은 사회를 만들어 살면서 거칠고 난폭한 개체를 사형 제도로 제거하며 약 10만년 이상 스스로를 길들였다."
    },
    {
      "question": "길들여진 종의 신체적 특징은 무엇인가?",
      "answer": "두개골이 동그래지고, 암컷과 수컷의 몸 크기가 비슷해지며, 나이가 들어도 어린 얼굴을 유지한다. 현대 사회에서 동안이 미의 상징인 것도 이와 관련 있다."
    },
    {
      "question": "보노보 침팬지의 특징은 무엇인가?",
      "answer": "70만년 전 일반 침팬지와 분리되어 셀프 도메스티케이션이 가속화된 종이다. 성을 통해 사회적 긴장을 해소하며, 모계 중심의 평화로운 사회를 이룬다."
    },
    {
      "question": "네안데르탈인이 멸종한 이유는 무엇인가?",
      "answer": "셀프 도메스티케이션이 되지 않았기 때문으로 추정된다. 얼굴이 옆으로 퍼져 있고 우락부락한 외모는 길들여지지 않은 종의 특징이다."
    },
    {
      "question": "미각의 절반은 무엇인가?",
      "answer": "기억이다. 맛은 단순한 감각이 아니라 그 음식과 연결된 기억, 감정, 경험의 총합이다. 법정 스님이 임종 무렵 팥죽을 찾은 것도 어린 시절 기억 때문이다."
    },
    {
      "question": "잠을 제대로 자야 하는 이유는 무엇인가?",
      "answer": "서파수면 3-4단계의 깊은 잠에서 해마의 일화 기억이 대뇌피질로 이동하여 장기 기억으로 저장되기 때문이다. 잠을 못 자면 기억력이 감퇴한다."
    },
    {
      "question": "'써먹을 생각하지 마라'는 말의 의미는 무엇인가?",
      "answer": "보상이나 목적을 생각하며 공부하면 진정으로 즐길 수 없다. 즐기는 사람을 당할 수 없으며, 좋은 습관을 들이려면 조건 없이 즐거움 자체를 추구해야 한다."
    },
    {
      "question": "동물, 인간, 우주는 각각 무엇에 구속되는가?",
      "answer": "동물은 감각에 구속되고, 인간은 의미에 구속되며, 우주는 중력에 구속된다."
    },
    {
      "question": "기억이 있어야 눈물을 흘릴 수 있는 이유는 무엇인가?",
      "answer": "정서와 감정은 기억과 결합되어 있기 때문이다. 기억이 다르면 정서를 공유하기 어렵다."
    },
    {
      "question": "뇌 활동에서 시각 정보가 차지하는 비율은 얼마나 되는가?",
      "answer": "약 80%다. 인간은 시각 위주로 진화해왔으며, 현대 사회는 점점 더 시각적으로 변화하고 있다."
    }
  ]
}