{
  "version": 1,
  "items": [
    {
      "question": "조토(Giotto di Bondone)는 누구이며, 미술사에서 어떤 위치를 차지하는가?",
      "answer": "1267년생 이탈리아 화가로 단테의 친구였다. 미술사에서 중세를 끝내고 근대 미술의 첫 발걸음을 뗀 인물로, 미술사 교과서에서 중세와 근대를 나누는 기점이 된다."
    },
    {
      "question": "조토가 미술사에서 혁명적인 이유는 무엇인가?",
      "answer": "수백 년간 불변이었던 비잔틴 이콘 미술의 전통을 깨고, 천상의 신성이 아닌 지상의 현실을 그리기 시작했다. 현대적 회화의 원리들(구도, 색감, 비례)을 최초로 도입했다."
    },
    {
      "question": "중세 미술의 역사관과 세계관은 어떠했는가?",
      "answer": "창세기부터 타락과 몰락의 역사관을 가졌다. 창조 시절의 완벽한 상태에서 점점 인간이 타락해 언제 세상이 끝날지 모른다는 종말론적 세계관이었다."
    },
    {
      "question": "비잔틴 이콘 미술의 특징은 무엇인가?",
      "answer": "수백 년간 불변의 도상 규칙을 따랐다. 금색을 많이 사용하고, 평면적이며 무중력 느낌의 인물들, 유려하고 세련된 선들이 특징이다. 마리아의 각도, 눈코입 비율 등이 모두 정해져 있었다."
    },
    {
      "question": "비잔틴 미술에서 이콘이 가진 의미는 무엇인가?",
      "answer": "이콘 자체를 신성하게 여겼으며, 실물보다 이콘이 진짜 실체라고 봤다. 이콘이 기적을 행사한다고 믿었고(치유, 예언 등), 전쟁 시 국기처럼 사용했다."
    },
    {
      "question": "조토가 화가의 길로 들어서게 된 계기는?",
      "answer": "가난한 양치기 소년이었던 조토가 돌판에 양을 사생하여 그렸다. 지나가던 화가 치마부에가 이를 보고 재능을 발견하여 제자로 데려갔다."
    },
    {
      "question": "조토의 양 그림이 혁명적이었던 이유는?",
      "answer": "최초로 '사생(실제 대상을 보고 그림)'을 했기 때문이다. 그 이전까지는 모델북의 도상을 암기하여 그렸는데, 조토는 눈앞의 살아있는 동물을 직접 관찰하여 그렸다."
    },
    {
      "question": "우피치 미술관의 조토 마에스타(마리아와 아기 예수)가 혁신적인 이유는?",
      "answer": "마리아를 떡 벌어진 어깨와 큰 엉덩이를 가진 육중한 실제 여성처럼 그렸다. 비잔틴 이콘의 무중력적이고 완벽한 마리아와 달리, 체중이 느껴지고 의자가 부서질 것 같은 현실감을 표현했다."
    },
    {
      "question": "파도바 스크로베니 경당은 무엇이며, 왜 중요한가?",
      "answer": "조토가 1304-1306년경 프레스코화로 장식한 경당이다. 4층 구조로 마리아와 예수의 생애를 그렸으며, 조토의 대표작들이 집중된 곳으로 미술사적으로 매우 중요하다."
    },
    {
      "question": "조토의 '애도(Lamentation)' 작품의 혁신적 특징은?",
      "answer": "금색을 사용하지 않았고, 인물들이 무작위로 배치되었으며, 주인공과 엑스트라의 키가 비슷하다. 모든 인물에게 화려한 색을 주었고, 등을 돌린 인물을 그려 '등에 표정'을 넣었다."
    },
    {
      "question": "'애도' 작품에서 등을 돌린 두 여성이 중요한 이유는?",
      "answer": "비잔틴 미술에서는 인물이 등을 돌리는 것이 금기였다. 조토는 등을 돌리고 얼굴도 보이지 않게 그려, 처진 어깨와 자세만으로 슬픔을 표현하고 관객의 상상력을 자극했다."
    },
    {
      "question": "비잔틴 미술에서 인물 크기는 어떻게 결정되었나?",
      "answer": "'가치비례' 원칙을 따랐다. 중요한 인물일수록 크게, 덜 중요한 인물은 작게 그렸다. 주인공은 엑스트라보다 훨씬 큰 사이즈로 표현되었다."
    },
    {
      "question": "조토는 '애도' 작품에서 인물 크기를 어떻게 처리했나?",
      "answer": "주인공(예수, 마리아)과 주변 인물들의 키를 모두 비슷하게 그렸다. 중요도가 아닌 현실적 비례를 따랐으며, 이는 현대적 회화 원리의 시작이었다."
    },
    {
      "question": "'애도' 작품의 고목과 새순 모티프는 무엇을 상징하는가?",
      "answer": "앙상한 겨울 나무 끝에서 파란 이파리가 돋아나는 모습으로 죽음과 부활, 구원을 상징한다. 예수의 죽음 이후 부활을 예견하는 장치이다."
    },
    {
      "question": "조토의 '예루살렘 성전에서 쫓겨나는 요아킴' 작품의 배경은?",
      "answer": "성모 마리아의 아버지 요아킴이 80세까지 자식이 없어 성전에 제물을 바치려다 '저주받았다'며 쫓겨나는 장면이다. 야코부스 다 보라기네의 『황금 전설』에 기록된 이야기이다."
    },
    {
      "question": "조토가 그린 솔로몬 성전의 소용돌이 기둥은 무엇을 의미하는가?",
      "answer": "콘스탄티누스 황제가 구 베드로 대성당에 설치한 소용돌이 기둥을 그렸다. 이는 역사적 고증을 시도한 것으로, 조토가 실제 본 것을 바탕으로 그렸음을 보여준다."
    },
    {
      "question": "'황금 문의 만남' 에피소드는 무엇인가?",
      "answer": "6개월간 가출했던 요아킴과 아내 안나가 각각 천사의 지시로 예루살렘 황금 문에서 만나 키스했다. 80세 노부부의 이 '황금의 키스'로 성모 마리아가 잉태되었다는 이야기이다."
    },
    {
      "question": "조토의 '라자로의 부활' 작품에서 악취는 어떻게 표현되었나?",
      "answer": "한 인물이 파란 옷자락으로 코를 가리는 모습으로 표현했다. 죽은 지 나흘 된 라자로의 부패 냄새를 시각적으로 나타낸 것이다(단, 조토가 최초는 아님)."
    }
  ]
}