{
  "version": 1,
  "items": [
    {
      "question": "시벨리우스가 사망한 날의 일화는?",
      "answer": "91세에 산책 후 부인에게 새들이 나는 것을 봤고 그 중 한 마리가 집 쪽으로 날았다고 말한 그날 사망했다. 핀란드 정부는 그가 백조가 되어 하늘로 날아갔다며 상공 항공편을 결항시켰다."
    },
    {
      "question": "시벨리우스 음악의 전반적 특징은?",
      "answer": "슬프고 애잔하며 우울하고 외로운 감정 표현에 뛰어났다. 쓸쓸하고 스산한 분위기가 독특하며, 웅장함 속에도 긴 대선율로 사람을 고취시키는 고급스러운 음악이다."
    },
    {
      "question": "시벨리우스가 건강이 나빠진 시기와 원인은?",
      "answer": "50대 핀란드 내전 시기에 알코올 중독과 과도한 흡연으로 건강이 크게 나빠졌다. 원래는 매우 건강한 사람이었으나 이 시기에 머리를 밀기도 했다."
    },
    {
      "question": "핀란드 내전 당시 시벨리우스 부부의 정치적 성향은?",
      "answer": "시벨리우스는 우파(독일) 쪽으로, 부인은 좌파(러시아) 쪽으로 기울었다. 결국 우파가 승리했고, 3개월간 약 3만 명이 희생되었다."
    },
    {
      "question": "핀란드가 독립하게 된 과정은?",
      "answer": "러시아 혁명(볼셰비키) 이후 내전이 발생했고, 독일 지원을 받은 우파가 승리했다. 이후 1차 세계대전에서 독일이 패배하면서 준비되지 않은 채 갑자기 독립하게 되었다."
    },
    {
      "question": "시벨리우스가 나치와 연관된 부분은?",
      "answer": "나치로부터 상을 받은 적이 있으나, 적극적으로 활동한 것은 아니다. 핀란드가 독립 과정에서 독일의 지원을 받았던 역사적 배경과 관련이 있다."
    },
    {
      "question": "시벨리우스 공연에서 자주 발생하는 해프닝은?",
      "answer": "교향곡 1악장이 끝날 때 곡이 끝난 줄 알고 관객들이 잘못 박수를 치는 경우가 많다. 길이도 길고 마지막이 훅 끝나기 때문에 정신을 못 차린다."
    },
    {
      "question": "핀란드 오케스트라가 자주 앵콜로 연주하는 시벨리우스 곡은?",
      "answer": "'투오넬라의 백조'. 분위기 있게 공연을 마감할 때 앵콜곡으로 자주 연주된다."
    },
    {
      "question": "시벨리우스 가문의 현재 위상은?",
      "answer": "다섯 명의 딸들이 유명 인사가 되거나 유명인과 결혼하여, 핀란드 최고의 가문 중 하나로 자리잡았다."
    },
    {
      "question": "시벨리우스가 독일과 비엔나를 방문한 이유와 결과는?",
      "answer": "핀란드에서는 음악 배우기 어려워 독일과 비엔나를 방문했으나, 둘 다 자신과 맞지 않는다고 생각했다. 결국 핀란드로 돌아와 모교 음악학교 교수로 생계를 유지했다."
    },
    {
      "question": "시벨리우스 음악이 우리나라 자연환경과 맞는 이유는?",
      "answer": "고속도로 운전할 때 듣기 좋으며, 미끄러져 가는 웅장함이 있다. 스산하고 쓸쓸한 분위기가 한국의 정서와도 통한다."
    },
    {
      "question": "시벨리우스 교향곡의 음악적 철학은?",
      "answer": "모든 악기가 살아있는 것처럼 유기적으로 연결된, 마치 실을 짜듯이 짜여진 음악을 추구했다. 형식보다는 유기적 연결을 중시했다."
    },
    {
      "question": "시벨리우스가 낭만주의 음악을 고수한 이유는?",
      "answer": "현대 음악으로의 전환을 시도했으나 성공하지 못했고, 결국 과거 낭만주의를 고수했다. 하지만 단순한 과거 수준이 아니라 차원을 높인 수준 높은 낭만주의 음악을 작곡했다."
    },
    {
      "question": "핀란드를 상징하는 '두 마리의 유명한 새'는?",
      "answer": "투오넬라의 백조와 앵그리버드."
    },
    {
      "question": "시벨리우스가 평생 강조한 가장 행복했던 순간은?",
      "answer": "학 십여 마리가 한꺼번에 날아가는 모습을 목격한 순간. 이 경험이 교향곡 5번 완성의 영감이 되었으며, 사망 당일에도 비슷한 경험을 부인에게 이야기했다."
    }
  ]
}