{
  "version": 1,
  "items": [
    {
      "question": "김홍기 목사가 2011년 서울시 자문위원 해촉된 사건의 배경은 무엇인가?",
      "answer": "오세훈 시장 때 세빛둥둥섬에서 펜디 모피 쇼가 열렸고, 동물보호 시위대 앞에서 중앙일보 인터뷰 시 '크루얼 프리(동물 학대 없는)' 친환경 관점 도입을 주장했다가 일주일 후 해촉되었다."
    },
    {
      "question": "비건이란 정확히 무엇을 의미하는가?",
      "answer": "동물성 식품뿐 아니라 모피, 가죽 등 동물로부터 나오는 모든 소재를 사용하지 않는 생활 방식이다. 완벽한 비건은 생선도 먹지 않는다."
    },
    {
      "question": "'왜 우리는 개는 사랑하고 돼지는 먹고 소는 신나'는 책 제목이 제기하는 문제는 무엇인가?",
      "answer": "반려동물에게는 정서적 유대를 보이면서 다른 동물들은 식용이나 소재로 사용하는 종별 차별(speciesism)의 모순을 지적한다."
    },
    {
      "question": "비건 주장에 따른 육식의 문제점은 무엇인가?",
      "answer": "쇠고기 113g을 얻기 위해 1730리터의 물이 필요하고, 소를 키우는데 인간이 사는 땅의 20배를 사용해야 한다. 경제적으로도 지속 가능하지 않다."
    },
    {
      "question": "비건 패션이란 무엇인가?",
      "answer": "모피, 가죽 등 동물의 부산물을 사용하지 않고 식물성 원료나 재활용 소재로 만드는 패션을 말한다."
    },
    {
      "question": "가죽 제조 과정이 환경에 미치는 영향은 무엇인가?",
      "answer": "동물 가죽이 썩지 않도록 크롬 등 화학약품으로 무두질(태닝)하고, 염색 과정에서 대량의 화학 폐수가 발생한다. 패션 산업은 정유 산업 다음으로 환경을 오염시키는 산업 2위다."
    },
    {
      "question": "비건 가죽의 원료로 사용되는 소재들은 무엇인가?",
      "answer": "버섯, 파인애플 껍질(피냐텍스), 선인장, 코르크, 포도 껍질, 파인애플 잎 등 다양한 식물성 원료가 사용된다."
    },
    {
      "question": "식물성 가죽이 동물 가죽보다 나은 점은 무엇인가?",
      "answer": "바이오디그레이더블(생분해성)이어서 자연에서 썩어 순환된다. 동물 가죽은 화학처리로 썩지 않게 만들어 환경 문제를 일으킨다."
    },
    {
      "question": "에르메스도 비건 가죽을 사용하기 시작했다는 것의 의미는 무엇인가?",
      "answer": "가죽으로 유명한 최고급 명품 브랜드조차 버섯 가죽(마일로) 등 친환경 소재를 채택하기 시작했다는 것은 패션 산업 전체가 지속 가능성으로 급속히 전환하고 있음을 보여준다."
    },
    {
      "question": "페타(PETA)는 무엇이며 어떤 활동을 하는가?",
      "answer": "'동물의 윤리적 처우를 위한 모임(People for the Ethical Treatment of Animals)'으로, 온몸에 피칠갑을 하고 모피 매장 앞에서 시위하는 등 강렬한 방식으로 동물 학대 반대 운동을 한다."
    },
    {
      "question": "RE100이란 무엇이며, 현 정부의 인식 수준은 어떠한가?",
      "answer": "재생에너지 100% 사용 캠페인인데, 대통령이 토론에서 처음 들어본다고 답했다. 유럽은 친환경 기준 미달 제품의 시장 진입을 막고 있어 수출에 치명적이다."
    },
    {
      "question": "DTP 염색 기술이란 무엇이며 장점은 무엇인가?",
      "answer": "잉크젯 프린터처럼 필요한 부분에만 직접 염료를 찍어내는 기술로, 화학약품 사용과 폐수 발생량이 100분의 1로 줄어들고 필요한 양만큼만 생산할 수 있다."
    },
    {
      "question": "샌드 블래스팅이 금지된 이유는 무엇인가?",
      "answer": "청바지의 워싱 효과를 내기 위해 모래가루를 뿌리는 작업인데, 작업 노동자들이 1년 만에 진폐증으로 사망할 정도로 위험하다. 유럽과 미국 등 선진국에서는 금지되었다."
    },
    {
      "question": "폴리에스테르 옷이 환경에 미치는 영향은 무엇인가?",
      "answer": "석유로 만든 폴리에스테르 옷을 세탁할 때마다 미세 플라스틱이 빠져나와 해양으로 유입되고 물고기가 섭취한다."
    }
  ]
}