{
  "version": 1,
  "items": [
    {
      "question": "세 명의 게스트가 공통적으로 강조한 '멘탈'의 중요성은?",
      "answer": "극한 대회에서 신체적 능력만큼이나 정신력이 중요하다. 외로움, 고통, 공포를 이겨내는 멘탈과 끈기가 완주의 핵심 요소다."
    },
    {
      "question": "세 대회 모두에서 '밤'이 중요한 이유는?",
      "answer": "밤에는 제대로 된 판단을 하기 어렵기 때문. 실크로드 매뉴얼에도 '밤에 선택하지 마라'는 조언이 있으며, 포기 결정도 자고 일어나서 해야 한다."
    },
    {
      "question": "박종하 씨가 실크로드 마운틴 레이스를 위한 평일 훈련은?",
      "answer": "강서에서 상계동까지 자전거로 왕복하며 하루 평균 100km 정도 탔다. 안장에 오래 앉아 있는 훈련이 가장 중요했다."
    },
    {
      "question": "박종하 씨가 주말에 한 훈련은?",
      "answer": "바이크 패킹으로 배낭, 텐트, 침낭을 메고 산에 가서 하루 이틀 야영하거나, 장거리 대회(200~600km)에 참가했다."
    },
    {
      "question": "세 게스트의 직업은 각각 무엇인가?",
      "answer": "박종하 씨는 전기 공사, 류명걸 씨는 라이딩 교육(과거 모터사이클 수입 판매 회사 근무), 최영석 씨는 회사원. 모두 프로가 아닌 일반인이다."
    },
    {
      "question": "세 게스트의 결혼 여부는?",
      "answer": "박종하 씨와 최영석 씨는 미혼(싱글). 류명걸 씨만 다카르 랠리 다녀온 후 결혼해 현재 두 자녀가 있다."
    },
    {
      "question": "다카르 랠리에서 경쟁 구간 중 화장실 문제는 어떻게 해결하나?",
      "answer": "소변은 팬티에 소변줄을 넣은 장비를 사용하기도 한다. 대변은 사전 배변 훈련으로 정해진 시간(새벽 출발 전)에 보도록 몸을 컨트롤한다."
    },
    {
      "question": "다카르 랠리 참가 시 도핑 테스트를 하는 이유는?",
      "answer": "10일 동안 연달아 달려야 하므로, 참가자가 너무 힘들어 마취 상태의 약물을 사용할까 봐 도핑 테스트를 중요하게 실시한다."
    },
    {
      "question": "다카르 랠리에서 류명걸 씨가 준비하지 못한 것은?",
      "answer": "사막 새벽의 추위에 대비한 두꺼운 장갑과 파카 잠바. 다른 프로 선수들은 큰 겨울용 스키 장갑과 두꺼운 옷을 준비했으나, 경험 부족으로 빼먹었다."
    },
    {
      "question": "실크로드 마운틴 레이스의 체크포인트는 몇 개이며 어디에 있나?",
      "answer": "총 세 곳. 약 500km, 1,300km, 1,500km 지점에 있다. 체크포인트는 체크만 하는 곳이고, 나머지는 알아서 야영하며 생존해야 한다."
    },
    {
      "question": "실크로드 마운틴 레이스에서 중간 포기 시 어떻게 되나?",
      "answer": "아무도 데리러 오지 않는다. 본인이 근처 도착지까지 가야 한다. 도착지에 본인 짐이 있기 때문이다."
    },
    {
      "question": "실크로드 마운틴 레이스 참가자들의 특징은?",
      "answer": "처음 오는 사람은 박종하 씨밖에 없었고, 대부분 비슷한 대회 완주 경험이 많은 사람들이다. 자전거 레이스 중 가장 어려운 대회라 끝판왕을 경험하려는 사람들이 모인다."
    },
    {
      "question": "류명걸 씨가 다카르 랠리 준비를 위해 포기한 것은?",
      "answer": "10년 직장 생활을 퇴사하고, 퇴직금과 전세 자금을 다카르 랠리 준비에 투자했다. 2년 동안 전업으로 훈련했다."
    },
    {
      "question": "극지 마라톤에서 대회 측이 제공하는 것은?",
      "answer": "캠프마다 텐트, 물, 뜨거운 물만 제공한다. 나머지는 모두 참가자가 준비해야 한다."
    },
    {
      "question": "극지 마라톤 4개 사막의 순서는?",
      "answer": "사하라(아프리카), 고비(몽골), 아타카마(칠레), 남극 순서로 진행된다."
    },
    {
      "question": "세 게스트가 극한 대회에 도전하는 공통된 이유는?",
      "answer": "박종하 씨는 별과 자연 경험, 류명걸 씨는 살아있음을 느끼는 것, 최영석 씨는 후회 없는 삶. 모두 자기 만족과 성취감을 위해 도전한다."
    },
    {
      "question": "실크로드 마운틴 레이스 참가 희망자에게 박종하 씨의 조언은?",
      "answer": "완주 못 해도 좋은 경험을 할 수 있으니 가고 싶으면 꼭 가보라고 한다. 코스 맵, 준비물 등 자세한 정보를 알려주겠다고 했다."
    },
    {
      "question": "류명걸 씨가 다카르 랠리 재도전에 대해 가진 생각은?",
      "answer": "부인에게 한 번으로 끝내겠다고 약속했다. 비용 충당이 가장 힘들었기 때문. 하지만 계속 밑밥은 던지고 있다고 했다."
    },
    {
      "question": "세 게스트가 공통적으로 강조한 '도전'의 의미는?",
      "answer": "류명걸 씨는 계속 새로운 것에 도전하는 게 인간이 해야 할 일이라고 했다. 머물러 있지 않고 계속 도전하는 삶을 강조했다."
    }
  ]
}