{
  "version": 1,
  "items": [
    {
      "question": "옥단춘이 김진희의 수청을 거부하지 않고 받아들인 이유는?",
      "answer": "완전히 거부하면 자신도 위험하고, 재산을 모을 기회를 잃기 때문이다. 대신 건성으로 대응하며 비위만 맞추고, 동시에 다음 기회(이혈룡)를 엿보는 현실적 전략을 택했다."
    },
    {
      "question": "이혈룡이 과거를 보러 가면서도 집에 가지 않은 이유는?",
      "answer": "옥단춘이 시킨 대로 이선부 댁으로 가라고 했고, 집에 가면 볼 낯이 없고 두려웠기 때문이다. 옥단춘의 지시를 따르는 것이 더 안전하다고 판단했다."
    },
    {
      "question": "이혈룡의 어머니와 부인이 평양 감사를 칭찬한 진짜 이유는?",
      "answer": "실제로는 옥단춘이 보낸 돈이지만 평양 감사가 보낸 것으로 알고 있었기 때문이다. 옥단춘의 전략이 성공하여 가족들이 감사해하고 있었다."
    },
    {
      "question": "이혈룡이 임금에게 상소를 올린 방식이 보여주는 그의 한계는?",
      "answer": "직접 가서 김진희를 처벌하거나 대면하는 것이 아니라 임금에게 일러바치는 방식을 택했다. 스스로 해결하지 못하고 상급자에게 의존하는 수동적 태도를 보여준다."
    },
    {
      "question": "임금이 세 개의 봉서를 단계적으로 뜯게 한 이유는?",
      "answer": "작가의 빌드업 기법으로, 독자의 궁금증을 유발하고 긴장감을 높이기 위함이다. 한 번에 다 알려주면 재미가 없기 때문에 단계적으로 공개했다."
    },
    {
      "question": "옥단춘이 이혈룡의 거짓 실패담을 들으며 생각한 것은?",
      "answer": "이미 모든 것을 알고 있으면서도 모르는 척 위로하며, 이것이 이혈룡의 마지막 테스트이자 자신에 대한 충성도를 확인하는 기회로 활용했다."
    },
    {
      "question": "이혈룡이 '대장부가 근심하면 큰일'이라는 옥단춘의 말에 반응한 것은?",
      "answer": "'아 내가 암행어사 출도한 다음에 얘를 꼭 데리고 가야 되겠다'는 결심을 했다. 옥단춘의 마지막 퍼포먼스가 성공한 것이다."
    },
    {
      "question": "암행어사 출두 장면이 두 번째 연광정 잔치까지 늦춰진 극적 효과는?",
      "answer": "김진희의 악행을 더 부각시키고, 옥단춘까지 위험에 빠뜨려 긴장감을 최고조로 끌어올렸다. 마지막 역전의 카타르시스를 극대화하기 위한 장치였다."
    },
    {
      "question": "이혈룡이 '물귀신'이라고 한 장면의 장르적 변화는?",
      "answer": "갑자기 귀신 이야기가 나오며 장르가 튀는 순간이다. 나중에 김진희가 '귀신이 시켰다'고 변명하는 것과 연결되며, 초자연적 요소를 암시한다."
    },
    {
      "question": "이혈룡이 김진희를 완전히 죽이지 않고 고문만 하라고 한 이유는?",
      "answer": "선대의 정, 즉 부모들의 우정 때문이다. 우유부단하지만 인간적인 면이 있어 친구를 직접 죽이는 것까지는 할 수 없었다. 이것이 이혈룡의 유일한 장점이다."
    },
    {
      "question": "번개로 김진희를 죽인 것이 세계 문학에서 유일하다고 평가한 이유는?",
      "answer": "주인공이 원수를 직접 갚거나 용서하는 엔딩은 흔하지만, 번개(천벌)로 해결하는 방식은 극히 드물다. '마른 날의 날벼락'으로 작가의 딜레마를 해결한 독창적 발상이다."
    },
    {
      "question": "이혈룡이 '나를 원망하지 말거라'고 한 대사가 보여주는 것은?",
      "answer": "마지막까지 우유부단하고 책임을 회피하는 성격을 보여준다. 친구를 죽이지는 않았지만 그렇다고 적극적으로 구하지도 못한 자신의 처지를 변명하는 것이다."
    },
    {
      "question": "옥단춘이 평양 감사의 부인이 된 후 한 역할은?",
      "answer": "남편 이혈룡이 재상이 되는 동안 재산도 많이 불리고 뒤에서 모든 것을 조정했다. 나라가 태평하게 된 것도 옥단춘의 기여가 컸을 것으로 추정된다."
    },
    {
      "question": "이혈룡의 결정들이 실제로는 누구의 것이었다고 해석되는가?",
      "answer": "모두 옥단춘이 한 것으로 봐야 한다. 이혈룡은 스스로 결정하는 능력이 없고 우유부단하므로, 옥단춘이 섭정처럼 뒤에서 모든 것을 결정했을 것이다."
    },
    {
      "question": "옥단춘전에서 연구자들이 놓친 핵심은 무엇인가?",
      "answer": "이혈룡의 찌질함과 옥단춘의 주도면밀한 리스크 테이킹을 제대로 포착하지 못했다. 이혈룡을 보고 상황을 판단하여 실행하는 옥단춘의 관점에서 작품을 봐야 매력이 드러난다."
    },
    {
      "question": "옥단춘이 '국정원을 하면 잘하겠다'는 평가를 받은 이유는?",
      "answer": "광범위한 정보망, 치밀한 계획, 선투자 전략, 모든 상황을 통제하는 능력, 모르는 척 연기하는 능력 등 첩보 및 전략 능력이 탁월하기 때문이다."
    },
    {
      "question": "태몽에서 청룡과 백호가 싸운 것의 최종적 의미는?",
      "answer": "처음부터 이혈룡(청룡)이 김진희(백호)를 이기는 것이 운명적으로 정해져 있었다. 번개는 용의 권능이므로 결국 용이 백호를 처단한 것으로 태몽이 실현된 것이다."
    },
    {
      "question": "옥단춘이 임금을 해야 한다는 평가의 근거는?",
      "answer": "치밀한 계획 수립, 정보 수집 능력, 인재를 알아보는 안목, 장기적 투자, 위험 관리, 모든 상황을 통제하는 능력 등 통치자에게 필요한 자질을 모두 갖췄기 때문이다."
    },
    {
      "question": "옥단춘전이 현대적으로 해석될 가치가 있는 이유는?",
      "answer": "여성 주인공의 주체적 신분 상승, 전략적 사고, 리스크 관리, 정보 활용, 선투자 개념 등 현대적 경영 및 전략 개념이 담겨 있어 새롭게 해석할 여지가 많기 때문이다."
    }
  ]
}