{
  "version": 1,
  "items": [
    {
      "question": "고대 그리스인의 관점에서 스포츠를 무엇으로 보았으며, 이 관점의 특별함은?",
      "answer": "뇌와 근육의 커가는 우정으로 보았다. 다른 기능들(전쟁 준비, 분쟁 해결, 자기최적화)과 달리 이 관점은 매우 독특하고 대체하기 어렵다."
    },
    {
      "question": "현대 유전자 연구가 스포츠에 대해 밝혀낸 결론은 무엇인가?",
      "answer": "유전적으로(그리고 그리스적으로) 보면 스포츠는 근육과 뇌 사이의 진정으로 자극적인 대화라는 것이다. 이를 위해 수백 명을 운동 전후로 수만 개 유전자를 검사하고 복잡한 알고리즘으로 분석해야 했다."
    },
    {
      "question": "뇌가 근육을 통해 얻는 것은 무엇인가?",
      "answer": "근육을 통해 뇌는 실제 세계의 여러 차원을 체험하며, 원하는 대로 그냥 생각해낼 수 없다. 나무토막은 떨어지거나 떨어지지 않거나 둘 중 하나다."
    },
    {
      "question": "근육량/운동성 유전자와 뇌는 훈련에 대해 어떻게 다르게 반응하는가?",
      "answer": "근육량·운동성 유전자는 훈련으로 결정적으로 변하지 않는다(있거나 없거나다). 반면 뇌는 모든 종류의 움직임에 매우 민감하게 반응하며 변화한다. 팔이 가늘게 남더라도 머릿속은 매우 달라진다."
    },
    {
      "question": "단 한 번의 운동 단위 후에도 뇌에서 일어나는 변화는 무엇인가?",
      "answer": "뇌는 이후 몇 시간 동안 도파민 수용체의 수를 조절한다. 도전적 움직임을 따라가기 위해 뇌 자체의 성장인자(Wachstumsfaktoren) 생산을 촉진해 새로운 뇌세포가 생길 수 있는데, 이는 의학적으로 오랫동안 불가능하다고 여겨졌던 일이다."
    },
    {
      "question": "규칙적 운동과 그로 인해 생긴 신경은 어떤 질병을 예방하는가?",
      "answer": "신경세포가 손상되는 질병, 즉 치매, 우울증, 파킨슨병을 예방한다."
    },
    {
      "question": "스포츠가 유전자에 미치는 영향은 어느 정도인가?",
      "answer": "스포츠는 수백 개의 서로 다른 유전자의 조절(Modulation)을 일으킨다. 비교할 만한 효과를 가진 다른 활동은 거의 없다."
    },
    {
      "question": "유전적 효과를 위해 표준적인 스포츠가 꼭 필요한가?",
      "answer": "필요하지 않다. 다양한 방식으로 숨 쉬기, 춤추기(신경학적으로 무게 들기와 동등), 함께 하이킹·자전거 타기, 음악 들으며 청소하기도 뇌와 근육의 즐거운 만남이 된다. 중요한 것은 둘이 의무가 아니라 함께 무언가를 체험하는 것이다."
    },
    {
      "question": "우리에게 잘 맞는 스포츠가 유전적으로 미리 정해질 수 있는데, 연구가 특히 주목한 두 유전자는 무엇인가?",
      "answer": "ACTN3 유전자와 ACE 유전자다."
    },
    {
      "question": "ACTN3 유전자는 무슨 기능을 하며, 이를 가진 사람의 특징은?",
      "answer": "그 산물인 알파-액티닌-3(Alpha-Actinin-3)로 근육의 단백질 발을 안정화한다. 이 유전자를 가진 사람은 단거리 달리기에 더 유리한 경향이 있다."
    },
    {
      "question": "ACTN3 유전자가 없는 사람의 특징은 무엇인가?",
      "answer": "특히 북반구에 이 유전자가 없는 사람이 많다. 이들의 근육 발은 더 느리게 움직이며 더 많은 열을 방출해 추위 내성이 높다. 예를 들어 많은 스칸디나비아인이 떨지 않고 얼음물에서 더 오래 수영할 수 있다."
    },
    {
      "question": "ACE 유전자는 무엇에 영향을 미치는가?",
      "answer": "혈압에 영향을 준다. 유전자 변이에 따라 평균 혈압과 근육의 산소·영양 공급 정도가 달라진다."
    },
    {
      "question": "ACE-D 변이를 가진 사람의 특징과 적합한 운동은?",
      "answer": "평균 혈압이 다소 높아 휴식 시에도 근육에 산소와 영양이 강하게 공급된다. 휴식 후에도 빠르게 최고 성과가 가능해 근력 운동(Kraftsport)에 유리하다."
    },
    {
      "question": "ACE-I 변이를 가진 사람의 특징과 어떤 운동인에게 많은가?",
      "answer": "혈압이 비교적 낮아 긴 노력 시 에너지를 절약한다. 마라톤 주자와 등반가 중에 이 변이를 가진 사람이 훨씬 많다."
    },
    {
      "question": "ACE 억제제(ACE-Hemmer)란 무엇인가?",
      "answer": "혈압을 낮추기 위해 ACE 유전자의 산물을 표적으로 삼는 약물이다. 주로 앉아서 지내는 사람들에게 높은 혈압은 불리하기 때문에 사용된다."
    },
    {
      "question": "코로나 팬데믹 동안 ACE 유전자가 주목받은 이유는 무엇인가?",
      "answer": "SARS-CoV-2 바이러스가 특정 ACE 수용체에 결합할 수 있기 때문이다. 동시에 고혈압인 사람이 더 자주 중증화되고, 지구력 운동을 하는 사람은 중증 경과를 덜 겪는다는 것이 관찰되었다."
    },
    {
      "question": "고혈압인 사람과 추위 내성이 좋은 사람에게 각각 적합한 운동은 무엇인가?",
      "answer": "고혈압인 사람에게는 짧은 조깅이나 근력 운동이 더 맞을 수 있다. 추위 내성이 좋은 사람에게는 지구력 운동과 긴 조깅이 적합하다."
    },
    {
      "question": "한 시간 연속 운동이 늘 불편한 사람에게 권할 만한 운동 형태는 무엇인가?",
      "answer": "짧고 강도 높은 훈련 단위가 더 잘 맞을 수 있다. 예를 들어 30초 전력과 30초 휴식을 반복하는 이른바 7분 운동(7-Minuten-Workout)이다."
    },
    {
      "question": "이 장에서 결론짓는 '효과적인 스포츠'의 본질은 무엇인가?",
      "answer": "스포츠는 단순한 작업치료가 아니라 놀이-스트레스이자 친근한 에너지 약탈자이며, 우정이 그렇듯 무의미하면서도 의미 있다. 미터나 킬로그램으로 측정될 필요가 없으며, 본질적으로 성과(Leistung)의 정반대로서 자기 자신 외 누구에게도 의미 있을 필요가 없다."
    }
  ]
}